[{"ptk_id":"cd8b072a-6b81-44b0-92ed-3e38fb410d51","semester_id":"20222","sekolah_id":"5027f66f-8b18-e111-bae6-1bd53619789e","ptk_terdaftar_id":"5541934d-9999-4370-921c-689194ca57f4","nama":"SITI SULYANI","nip":null,"jenis_kelamin":"P","tempat_lahir":"SENDANG ASIH","tanggal_lahir":"1991-11-17","nik":"1802226411910001","no_kk":null,"niy_nigk":null,"nuptk":null,"nuks":null,"status_kepegawaian":"Tenaga Honor Sekolah","jenis_ptk_id":"11","jenis_ptk":"Tenaga Administrasi Sekolah","pengawas_bidang_studi":null,"agama":"Islam","kewarganegaraan":"ID","alamat_jalan":"sendang mulyo","rt":null,"rw":null,"nama_dusun":null,"desa_kelurahan":"sendang mulyo","kode_kecamatan":"120218  ","kecamatan":"Kec. Sendang Agung","kode_kabupaten":"120200  ","kabupaten":"Kab. Lampung Tengah","kode_provinsi":"120000  ","provinsi":"Prov. Lampung","kode_pos":null,"lintang":null,"bujur":null,"no_telepon_rumah":null,"no_hp":"085709338507","email":"SULYANIBINTANG90@GMAIL.COM","status_keaktifan":"Aktif","sk_cpns":null,"tgl_cpns":null,"sk_pengangkatan":"420/03/02/C.22/D.1/2016","tmt_pengangkatan":"2016-07-13","lembaga_pengangkat":"Kepala Sekolah","pangkat_golongan":null,"keahlian_laboratorium":null,"sumber_gaji":"Sekolah","nama_ibu_kandung":"SITI KHOTIJAH","status_perkawinan":"1","nama_suami_istri":null,"nip_suami_istri":null,"pekerjaan_suami_istri":99,"tmt_pns":null,"sudah_lisensi_kepala_sekolah":"0","jumlah_sekolah_binaan":null,"pernah_diklat_kepengawasan":"0","nm_wp":null,"status_data":null,"karpeg":null,"karpas":null,"mampu_handle_kk":"0","keahlian_braille":"0","keahlian_bhs_isyarat":"0","npwp":null,"bank":null,"rekening_bank":null,"rekening_atas_nama":null,"tahun_ajaran":"2022/2023","nomor_surat_tugas":"420/03/02/C.22/D.1/2016","tanggal_surat_tugas":"2016-07-13","tmt_tugas":"2016-07-13","ptk_induk":"1","jenis_keluar":null,"tgl_ptk_keluar":null,"riwayat_kepangkatan_pangkat_golongan":null,"riwayat_kepangkatan_nomor_sk":null,"riwayat_kepangkatan_tanggal_sk":null,"riwayat_kepangkatan_tmt_pangkat":null,"riwayat_kepangkatan_masa_kerja_gol_tahun":null,"riwayat_kepangkatan_masa_kerja_gol_bulan":null,"riwayat_gaji_berkala_pangkat_golongan":null,"riwayat_gaji_berkala_nomor_sk":null,"riwayat_gaji_berkala_tanggal_sk":null,"riwayat_gaji_berkala_tmt_kgb":null,"riwayat_gaji_berkala_masa_kerja_tahun":null,"riwayat_gaji_berkala_masa_kerja_bulan":null,"riwayat_gaji_berkala_gaji_pokok":null,"inpassing_pangkat_golongan":null,"inpassing_no_sk_inpassing":null,"inpassing_tgl_sk_inpassing":null,"inpassing_tmt_inpassing":null,"inpassing_angka_kredit":null,"inpassing_masa_kerja_tahun":null,"inpassing_masa_kerja_bulan":null,"riwayat_sertifikasi_bidang_studi":null,"riwayat_sertifikasi_jenis_sertifikasi":null,"riwayat_sertifikasi_tahun_sertifikasi":null,"riwayat_sertifikasi_nomor_sertifikat":null,"riwayat_sertifikasi_nrg":null,"riwayat_sertifikasi_nomor_peserta":null,"riwayat_pendidikan_formal_bidang_studi":null,"riwayat_pendidikan_formal_jenjang_pendidikan":null,"riwayat_pendidikan_formal_gelar_akademik":null,"riwayat_pendidikan_formal_satuan_pendidikan_formal":null,"riwayat_pendidikan_formal_fakultas":null,"riwayat_pendidikan_formal_kependidikan":null,"riwayat_pendidikan_formal_tahun_masuk":null,"riwayat_pendidikan_formal_tahun_lulus":null,"riwayat_pendidikan_formal_nim":null,"riwayat_pendidikan_formal_status_kuliah":null,"riwayat_pendidikan_formal_semester":null,"riwayat_pendidikan_formal_ipk":null,"jumlah_anak":null,"tugas_tambahan_jabatan_ptk":null,"tugas_tambahan_sekolah":null,"tugas_tambahan_jumlah_jam":null,"tugas_tambahan_nomor_sk":null,"tugas_tambahan_tmt_tambahan":null,"tugas_tambahan_tst_tambahan":null,"riwayat_struktural_jabatan_ptk":null,"riwayat_struktural_sk_struktural":null,"riwayat_struktural_tmt_jabatan":null,"riwayat_fungsional_jabatan_fungsional":null,"riwayat_fungsional_sk_jabfung":null,"riwayat_fungsional_tmt_jabatan":null,"create_date":"2022-04-10T08:59:36.707000","last_update":"2022-04-11T09:29:39.207000","soft_delete_ptk_terdaftar":0,"soft_delete_rwy_kepangkatan":null,"soft_delete_riwayat_gaji_berkala":null,"soft_delete_inpassing":null,"soft_delete_rwy_sertifikasi":null,"soft_delete_rwy_pend_formal":null,"soft_delete_tugas_tambahan":null,"soft_delete_rwy_struktural":null,"soft_delete_rwy_fungsional":null},{"ptk_id":"19e19624-82a6-dd11-abcc-e3600d1bee7b","semester_id":"20222","sekolah_id":"5027f66f-8b18-e111-bae6-1bd53619789e","ptk_terdaftar_id":"b95964d5-ffd3-40e2-88b5-0ffc76955418","nama":"Sumiyem","nip":"196311231983032002","jenis_kelamin":"P","tempat_lahir":"SENDANGAGUNG","tanggal_lahir":"1963-11-23","nik":"1802226311630001","no_kk":null,"niy_nigk":null,"nuptk":"7455741642300003","nuks":"19023LO991202222169563","status_kepegawaian":"PNS","jenis_ptk_id":"20","jenis_ptk":"Kepala Sekolah","pengawas_bidang_studi":"lainnya","agama":"Islam","kewarganegaraan":"ID","alamat_jalan":"SENDANGREJO","rt":17,"rw":9,"nama_dusun":"SENDANGREJO","desa_kelurahan":"SENDANGREJO","kode_kecamatan":"120218  ","kecamatan":"Kec. Sendang Agung","kode_kabupaten":"120200  ","kabupaten":"Kab. Lampung Tengah","kode_provinsi":"120000  ","provinsi":"Prov. Lampung","kode_pos":"34174","lintang":null,"bujur":null,"no_telepon_rumah":"082248584796","no_hp":"085788509771","email":"Sumiyemspd63@gmail.com","status_keaktifan":"Aktif","sk_cpns":"143/UP/1983","tgl_cpns":"1983-03-01","sk_pengangkatan":"143/UP/1983","tmt_pengangkatan":"1983-03-01","lembaga_pengangkat":"Pemerintah Pusat","pangkat_golongan":"IV/a","keahlian_laboratorium":"Lainnya","sumber_gaji":"APBN","nama_ibu_kandung":"PONIYEM","status_perkawinan":"1","nama_suami_istri":"SUPARMIN.S.Pd","nip_suami_istri":"196009151982031012","pekerjaan_suami_istri":5,"tmt_pns":"1985-01-01","sudah_lisensi_kepala_sekolah":"1","jumlah_sekolah_binaan":0,"pernah_diklat_kepengawasan":"0","nm_wp":null,"status_data":0,"karpeg":null,"karpas":null,"mampu_handle_kk":"0","keahlian_braille":"0","keahlian_bhs_isyarat":"0","npwp":"872460654321000","bank":null,"rekening_bank":null,"rekening_atas_nama":null,"tahun_ajaran":"2022/2023","nomor_surat_tugas":"KP1401219GUIV31983","tanggal_surat_tugas":"1983-09-01","tmt_tugas":"1983-09-01","ptk_induk":"1","jenis_keluar":null,"tgl_ptk_keluar":null,"riwayat_kepangkatan_pangkat_golongan":"IV/b","riwayat_kepangkatan_nomor_sk":"823.4/785.1/VI.04/2018","riwayat_kepangkatan_tanggal_sk":"2018-10-22","riwayat_kepangkatan_tmt_pangkat":"2018-10-01","riwayat_kepangkatan_masa_kerja_gol_tahun":30,"riwayat_kepangkatan_masa_kerja_gol_bulan":7,"riwayat_gaji_berkala_pangkat_golongan":"IV/b","riwayat_gaji_berkala_nomor_sk":"823.4/0323/B.a.VII.04/2020","riwayat_gaji_berkala_tanggal_sk":"2020-01-06","riwayat_gaji_berkala_tmt_kgb":"2020-03-01","riwayat_gaji_berkala_masa_kerja_tahun":32,"riwayat_gaji_berkala_masa_kerja_bulan":0,"riwayat_gaji_berkala_gaji_pokok":5211500,"inpassing_pangkat_golongan":null,"inpassing_no_sk_inpassing":null,"inpassing_tgl_sk_inpassing":null,"inpassing_tmt_inpassing":null,"inpassing_angka_kredit":null,"inpassing_masa_kerja_tahun":null,"inpassing_masa_kerja_bulan":null,"riwayat_sertifikasi_bidang_studi":"Guru Kelas SD/MI","riwayat_sertifikasi_jenis_sertifikasi":"Sertifikasi Pendidik","riwayat_sertifikasi_tahun_sertifikasi":null,"riwayat_sertifikasi_nomor_sertifikat":"1071102702385","riwayat_sertifikasi_nrg":null,"riwayat_sertifikasi_nomor_peserta":"11120202710636","riwayat_pendidikan_formal_bidang_studi":"Guru Kelas SD/MI","riwayat_pendidikan_formal_jenjang_pendidikan":"S1","riwayat_pendidikan_formal_gelar_akademik":"Sarjana Pendidikan","riwayat_pendidikan_formal_satuan_pendidikan_formal":"","riwayat_pendidikan_formal_fakultas":"","riwayat_pendidikan_formal_kependidikan":"Ya","riwayat_pendidikan_formal_tahun_masuk":0,"riwayat_pendidikan_formal_tahun_lulus":2009,"riwayat_pendidikan_formal_nim":"tidak diisi","riwayat_pendidikan_formal_status_kuliah":"Tidak","riwayat_pendidikan_formal_semester":0,"riwayat_pendidikan_formal_ipk":0.0,"jumlah_anak":1,"tugas_tambahan_jabatan_ptk":"Kepala Sekolah","tugas_tambahan_sekolah":"(10801547) SD NEGERI 3 SENDANGREJO","tugas_tambahan_jumlah_jam":0,"tugas_tambahan_nomor_sk":"821.29/028/LTD.3/2012","tugas_tambahan_tmt_tambahan":"2012-02-15","tugas_tambahan_tst_tambahan":null,"riwayat_struktural_jabatan_ptk":"Kepala Sekolah","riwayat_struktural_sk_struktural":"****","riwayat_struktural_tmt_jabatan":"2012-02-15","riwayat_fungsional_jabatan_fungsional":null,"riwayat_fungsional_sk_jabfung":null,"riwayat_fungsional_tmt_jabatan":null,"create_date":"2018-01-24T11:23:02.553000","last_update":"2020-11-02T17:46:33.120000","soft_delete_ptk_terdaftar":0,"soft_delete_rwy_kepangkatan":0,"soft_delete_riwayat_gaji_berkala":0,"soft_delete_inpassing":null,"soft_delete_rwy_sertifikasi":0,"soft_delete_rwy_pend_formal":0,"soft_delete_tugas_tambahan":0,"soft_delete_rwy_struktural":0,"soft_delete_rwy_fungsional":null},{"ptk_id":"fcb672ac-2f4f-11e4-913e-0b306c94d82a","semester_id":"20222","sekolah_id":"5027f66f-8b18-e111-bae6-1bd53619789e","ptk_terdaftar_id":"6731bcb5-a9d7-43f5-9cec-396e700e9177","nama":"Fransisca Utari","nip":"199105172020122017","jenis_kelamin":"P","tempat_lahir":"SRIWAYLANGSEP","tanggal_lahir":"1991-05-17","nik":"1802225705910002","no_kk":"1802221701140002","niy_nigk":null,"nuptk":"3849769670130082","nuks":null,"status_kepegawaian":"PNS","jenis_ptk_id":"3 ","jenis_ptk":"Guru Kelas","pengawas_bidang_studi":null,"agama":"Islam","kewarganegaraan":"ID","alamat_jalan":"SENDANGASRI","rt":8,"rw":3,"nama_dusun":"3","desa_kelurahan":"SENDANGASRI","kode_kecamatan":"120218  ","kecamatan":"Kec. Sendang Agung","kode_kabupaten":"120200  ","kabupaten":"Kab. Lampung Tengah","kode_provinsi":"120000  ","provinsi":"Prov. Lampung","kode_pos":"34174","lintang":-5.156533460762,"bujur":104.9044947464,"no_telepon_rumah":null,"no_hp":"085357273151","email":"fransiscautari38@gmail.com","status_keaktifan":"Aktif","sk_cpns":"810/1419/B.a.VII.04/2020","tgl_cpns":"2020-12-21","sk_pengangkatan":"420/035/02/C.22/D.8/2014","tmt_pengangkatan":"2014-08-22","lembaga_pengangkat":"Pemerintah Kab/Kota","pangkat_golongan":"-","keahlian_laboratorium":null,"sumber_gaji":"APBN","nama_ibu_kandung":"WARDANI","status_perkawinan":"1","nama_suami_istri":"SUPRA WINATA","nip_suami_istri":null,"pekerjaan_suami_istri":9,"tmt_pns":"2022-12-01","sudah_lisensi_kepala_sekolah":"1","jumlah_sekolah_binaan":0,"pernah_diklat_kepengawasan":"0","nm_wp":null,"status_data":0,"karpeg":null,"karpas":null,"mampu_handle_kk":"0","keahlian_braille":"0","keahlian_bhs_isyarat":"0","npwp":"410001978321000","bank":null,"rekening_bank":null,"rekening_atas_nama":null,"tahun_ajaran":"2022/2023","nomor_surat_tugas":"810/1419/B.a.VII.04/2020","tanggal_surat_tugas":"2020-12-21","tmt_tugas":"2020-12-01","ptk_induk":"1","jenis_keluar":null,"tgl_ptk_keluar":null,"riwayat_kepangkatan_pangkat_golongan":"III/a","riwayat_kepangkatan_nomor_sk":"821.13/827/B.a.VII.04/2022","riwayat_kepangkatan_tanggal_sk":"2022-11-30","riwayat_kepangkatan_tmt_pangkat":"2022-12-01","riwayat_kepangkatan_masa_kerja_gol_tahun":2,"riwayat_kepangkatan_masa_kerja_gol_bulan":2,"riwayat_gaji_berkala_pangkat_golongan":"III/a","riwayat_gaji_berkala_nomor_sk":"810/1419/B.a.VII.04/2020","riwayat_gaji_berkala_tanggal_sk":"2020-12-21","riwayat_gaji_berkala_tmt_kgb":"2020-12-01","riwayat_gaji_berkala_masa_kerja_tahun":0,"riwayat_gaji_berkala_masa_kerja_bulan":0,"riwayat_gaji_berkala_gaji_pokok":2579400,"inpassing_pangkat_golongan":null,"inpassing_no_sk_inpassing":null,"inpassing_tgl_sk_inpassing":null,"inpassing_tmt_inpassing":null,"inpassing_angka_kredit":null,"inpassing_masa_kerja_tahun":null,"inpassing_masa_kerja_bulan":null,"riwayat_sertifikasi_bidang_studi":null,"riwayat_sertifikasi_jenis_sertifikasi":null,"riwayat_sertifikasi_tahun_sertifikasi":null,"riwayat_sertifikasi_nomor_sertifikat":null,"riwayat_sertifikasi_nrg":null,"riwayat_sertifikasi_nomor_peserta":null,"riwayat_pendidikan_formal_bidang_studi":"Biologi","riwayat_pendidikan_formal_jenjang_pendidikan":"S1","riwayat_pendidikan_formal_gelar_akademik":"Sarjana Pendidikan","riwayat_pendidikan_formal_satuan_pendidikan_formal":"","riwayat_pendidikan_formal_fakultas":"","riwayat_pendidikan_formal_kependidikan":"Ya","riwayat_pendidikan_formal_tahun_masuk":2008,"riwayat_pendidikan_formal_tahun_lulus":2013,"riwayat_pendidikan_formal_nim":"09321279","riwayat_pendidikan_formal_status_kuliah":"Tidak","riwayat_pendidikan_formal_semester":8,"riwayat_pendidikan_formal_ipk":300.0,"jumlah_anak":1,"tugas_tambahan_jabatan_ptk":null,"tugas_tambahan_sekolah":null,"tugas_tambahan_jumlah_jam":null,"tugas_tambahan_nomor_sk":null,"tugas_tambahan_tmt_tambahan":null,"tugas_tambahan_tst_tambahan":null,"riwayat_struktural_jabatan_ptk":null,"riwayat_struktural_sk_struktural":null,"riwayat_struktural_tmt_jabatan":null,"riwayat_fungsional_jabatan_fungsional":null,"riwayat_fungsional_sk_jabfung":null,"riwayat_fungsional_tmt_jabatan":null,"create_date":"2018-01-24T11:23:02.553000","last_update":"2023-02-06T11:13:28.717000","soft_delete_ptk_terdaftar":0,"soft_delete_rwy_kepangkatan":0,"soft_delete_riwayat_gaji_berkala":0,"soft_delete_inpassing":null,"soft_delete_rwy_sertifikasi":null,"soft_delete_rwy_pend_formal":0,"soft_delete_tugas_tambahan":null,"soft_delete_rwy_struktural":null,"soft_delete_rwy_fungsional":null},{"ptk_id":"d76b9268-18b1-4804-91bf-5968070e1b75","semester_id":"20222","sekolah_id":"5027f66f-8b18-e111-bae6-1bd53619789e","ptk_terdaftar_id":"7e1bb7ea-50b8-4ff6-b773-19b71aa8e9da","nama":"DENI SETIAWATI","nip":null,"jenis_kelamin":"P","tempat_lahir":"SENDANG REJO","tanggal_lahir":"1997-09-12","nik":"1802225209970003","no_kk":null,"niy_nigk":null,"nuptk":null,"nuks":null,"status_kepegawaian":"Guru Honor Sekolah","jenis_ptk_id":"3 ","jenis_ptk":"Guru Kelas","pengawas_bidang_studi":null,"agama":"Islam","kewarganegaraan":"ID","alamat_jalan":"Dusun III","rt":null,"rw":null,"nama_dusun":null,"desa_kelurahan":"Sendang Rejo","kode_kecamatan":"120218  ","kecamatan":"Kec. Sendang Agung","kode_kabupaten":"120200  ","kabupaten":"Kab. Lampung Tengah","kode_provinsi":"120000  ","provinsi":"Prov. Lampung","kode_pos":null,"lintang":null,"bujur":null,"no_telepon_rumah":"085783201536","no_hp":"085161664388","email":"denisetiawati1000@gmail.com","status_keaktifan":"Aktif","sk_cpns":null,"tgl_cpns":null,"sk_pengangkatan":"420/04/C8/D.a/VI.01/2021","tmt_pengangkatan":"2021-03-10","lembaga_pengangkat":"Kepala Sekolah","pangkat_golongan":null,"keahlian_laboratorium":null,"sumber_gaji":"Sekolah","nama_ibu_kandung":"ARIYAH","status_perkawinan":"1","nama_suami_istri":"ANDI WIJAYANTO","nip_suami_istri":null,"pekerjaan_suami_istri":9,"tmt_pns":null,"sudah_lisensi_kepala_sekolah":"0","jumlah_sekolah_binaan":null,"pernah_diklat_kepengawasan":"0","nm_wp":null,"status_data":null,"karpeg":null,"karpas":null,"mampu_handle_kk":"0","keahlian_braille":"0","keahlian_bhs_isyarat":"0","npwp":null,"bank":null,"rekening_bank":null,"rekening_atas_nama":null,"tahun_ajaran":"2022/2023","nomor_surat_tugas":"420/04/C8/D.a/VI.01/2021","tanggal_surat_tugas":"2021-03-01","tmt_tugas":"2021-03-01","ptk_induk":"1","jenis_keluar":null,"tgl_ptk_keluar":null,"riwayat_kepangkatan_pangkat_golongan":null,"riwayat_kepangkatan_nomor_sk":null,"riwayat_kepangkatan_tanggal_sk":null,"riwayat_kepangkatan_tmt_pangkat":null,"riwayat_kepangkatan_masa_kerja_gol_tahun":null,"riwayat_kepangkatan_masa_kerja_gol_bulan":null,"riwayat_gaji_berkala_pangkat_golongan":null,"riwayat_gaji_berkala_nomor_sk":null,"riwayat_gaji_berkala_tanggal_sk":null,"riwayat_gaji_berkala_tmt_kgb":null,"riwayat_gaji_berkala_masa_kerja_tahun":null,"riwayat_gaji_berkala_masa_kerja_bulan":null,"riwayat_gaji_berkala_gaji_pokok":null,"inpassing_pangkat_golongan":null,"inpassing_no_sk_inpassing":null,"inpassing_tgl_sk_inpassing":null,"inpassing_tmt_inpassing":null,"inpassing_angka_kredit":null,"inpassing_masa_kerja_tahun":null,"inpassing_masa_kerja_bulan":null,"riwayat_sertifikasi_bidang_studi":null,"riwayat_sertifikasi_jenis_sertifikasi":null,"riwayat_sertifikasi_tahun_sertifikasi":null,"riwayat_sertifikasi_nomor_sertifikat":null,"riwayat_sertifikasi_nrg":null,"riwayat_sertifikasi_nomor_peserta":null,"riwayat_pendidikan_formal_bidang_studi":null,"riwayat_pendidikan_formal_jenjang_pendidikan":null,"riwayat_pendidikan_formal_gelar_akademik":null,"riwayat_pendidikan_formal_satuan_pendidikan_formal":null,"riwayat_pendidikan_formal_fakultas":null,"riwayat_pendidikan_formal_kependidikan":null,"riwayat_pendidikan_formal_tahun_masuk":null,"riwayat_pendidikan_formal_tahun_lulus":null,"riwayat_pendidikan_formal_nim":null,"riwayat_pendidikan_formal_status_kuliah":null,"riwayat_pendidikan_formal_semester":null,"riwayat_pendidikan_formal_ipk":null,"jumlah_anak":null,"tugas_tambahan_jabatan_ptk":null,"tugas_tambahan_sekolah":null,"tugas_tambahan_jumlah_jam":null,"tugas_tambahan_nomor_sk":null,"tugas_tambahan_tmt_tambahan":null,"tugas_tambahan_tst_tambahan":null,"riwayat_struktural_jabatan_ptk":null,"riwayat_struktural_sk_struktural":null,"riwayat_struktural_tmt_jabatan":null,"riwayat_fungsional_jabatan_fungsional":null,"riwayat_fungsional_sk_jabfung":null,"riwayat_fungsional_tmt_jabatan":null,"create_date":"2022-03-09T14:26:11.280000","last_update":"2022-03-10T13:29:31.693000","soft_delete_ptk_terdaftar":0,"soft_delete_rwy_kepangkatan":null,"soft_delete_riwayat_gaji_berkala":null,"soft_delete_inpassing":null,"soft_delete_rwy_sertifikasi":null,"soft_delete_rwy_pend_formal":null,"soft_delete_tugas_tambahan":null,"soft_delete_rwy_struktural":null,"soft_delete_rwy_fungsional":null},{"ptk_id":"80875079-8b18-e111-91d7-db21617e1fe6","semester_id":"20222","sekolah_id":"5027f66f-8b18-e111-bae6-1bd53619789e","ptk_terdaftar_id":"e4dfe439-ac2f-46c3-9ad2-4a25dd8ce7b0","nama":"Sumarmi","nip":"197007082022212002","jenis_kelamin":"P","tempat_lahir":"SENDANGREJO","tanggal_lahir":"1970-07-08","nik":"1802224807700003","no_kk":null,"niy_nigk":"1802224807710002","nuptk":"1040748647300003","nuks":null,"status_kepegawaian":"PPPK","jenis_ptk_id":"3 ","jenis_ptk":"Guru Kelas","pengawas_bidang_studi":"lainnya","agama":"Islam","kewarganegaraan":"ID","alamat_jalan":"Ds. 9","rt":16,"rw":9,"nama_dusun":"SENDANGREJO","desa_kelurahan":"SENDANGREJO","kode_kecamatan":"120218  ","kecamatan":"Kec. Sendang Agung","kode_kabupaten":"120200  ","kabupaten":"Kab. Lampung Tengah","kode_provinsi":"120000  ","provinsi":"Prov. Lampung","kode_pos":"34174","lintang":null,"bujur":null,"no_telepon_rumah":"085768513005","no_hp":"082373845692","email":"sumarmisd3rejo@gmail.com","status_keaktifan":"Aktif","sk_cpns":null,"tgl_cpns":null,"sk_pengangkatan":"810/460/B.a.VII.01/2022","tmt_pengangkatan":"2022-03-01","lembaga_pengangkat":"Pemerintah Kab/Kota","pangkat_golongan":"-","keahlian_laboratorium":"Lainnya","sumber_gaji":"Sekolah","nama_ibu_kandung":"PONIYEM","status_perkawinan":"3","nama_suami_istri":null,"nip_suami_istri":null,"pekerjaan_suami_istri":99,"tmt_pns":"2022-03-01","sudah_lisensi_kepala_sekolah":"0","jumlah_sekolah_binaan":0,"pernah_diklat_kepengawasan":"0","nm_wp":null,"status_data":0,"karpeg":null,"karpas":null,"mampu_handle_kk":"0","keahlian_braille":"0","keahlian_bhs_isyarat":"0","npwp":null,"bank":null,"rekening_bank":null,"rekening_atas_nama":null,"tahun_ajaran":"2022/2023","nomor_surat_tugas":"810/460/B.a.VII.01/2022","tanggal_surat_tugas":"2004-07-18","tmt_tugas":"2004-07-18","ptk_induk":"1","jenis_keluar":null,"tgl_ptk_keluar":null,"riwayat_kepangkatan_pangkat_golongan":null,"riwayat_kepangkatan_nomor_sk":null,"riwayat_kepangkatan_tanggal_sk":null,"riwayat_kepangkatan_tmt_pangkat":null,"riwayat_kepangkatan_masa_kerja_gol_tahun":null,"riwayat_kepangkatan_masa_kerja_gol_bulan":null,"riwayat_gaji_berkala_pangkat_golongan":null,"riwayat_gaji_berkala_nomor_sk":null,"riwayat_gaji_berkala_tanggal_sk":null,"riwayat_gaji_berkala_tmt_kgb":null,"riwayat_gaji_berkala_masa_kerja_tahun":null,"riwayat_gaji_berkala_masa_kerja_bulan":null,"riwayat_gaji_berkala_gaji_pokok":null,"inpassing_pangkat_golongan":null,"inpassing_no_sk_inpassing":null,"inpassing_tgl_sk_inpassing":null,"inpassing_tmt_inpassing":null,"inpassing_angka_kredit":null,"inpassing_masa_kerja_tahun":null,"inpassing_masa_kerja_bulan":null,"riwayat_sertifikasi_bidang_studi":null,"riwayat_sertifikasi_jenis_sertifikasi":null,"riwayat_sertifikasi_tahun_sertifikasi":null,"riwayat_sertifikasi_nomor_sertifikat":null,"riwayat_sertifikasi_nrg":null,"riwayat_sertifikasi_nomor_peserta":null,"riwayat_pendidikan_formal_bidang_studi":"Guru Kelas SD/MI","riwayat_pendidikan_formal_jenjang_pendidikan":"S1","riwayat_pendidikan_formal_gelar_akademik":"Sarjana Pendidikan","riwayat_pendidikan_formal_satuan_pendidikan_formal":"","riwayat_pendidikan_formal_fakultas":"","riwayat_pendidikan_formal_kependidikan":"Ya","riwayat_pendidikan_formal_tahun_masuk":0,"riwayat_pendidikan_formal_tahun_lulus":2014,"riwayat_pendidikan_formal_nim":"818387223","riwayat_pendidikan_formal_status_kuliah":"Tidak","riwayat_pendidikan_formal_semester":0,"riwayat_pendidikan_formal_ipk":0.0,"jumlah_anak":2,"tugas_tambahan_jabatan_ptk":null,"tugas_tambahan_sekolah":null,"tugas_tambahan_jumlah_jam":null,"tugas_tambahan_nomor_sk":null,"tugas_tambahan_tmt_tambahan":null,"tugas_tambahan_tst_tambahan":null,"riwayat_struktural_jabatan_ptk":"Guru","riwayat_struktural_sk_struktural":"****","riwayat_struktural_tmt_jabatan":"2004-07-18","riwayat_fungsional_jabatan_fungsional":null,"riwayat_fungsional_sk_jabfung":null,"riwayat_fungsional_tmt_jabatan":null,"create_date":"2018-01-24T11:23:02.553000","last_update":"2022-08-18T21:07:16.100000","soft_delete_ptk_terdaftar":0,"soft_delete_rwy_kepangkatan":null,"soft_delete_riwayat_gaji_berkala":null,"soft_delete_inpassing":null,"soft_delete_rwy_sertifikasi":null,"soft_delete_rwy_pend_formal":0,"soft_delete_tugas_tambahan":null,"soft_delete_rwy_struktural":0,"soft_delete_rwy_fungsional":null},{"ptk_id":"5df84c07-50a7-dd11-8ca8-fdfe1b036079","semester_id":"20222","sekolah_id":"5027f66f-8b18-e111-bae6-1bd53619789e","ptk_terdaftar_id":"22dc358f-395f-4b78-8696-d5b21fb45c6d","nama":"Rita Windayani","nip":"198506202022212012","jenis_kelamin":"P","tempat_lahir":"SUKOSARI","tanggal_lahir":"1985-06-20","nik":"1802016006850005","no_kk":null,"niy_nigk":"180802016006850008","nuptk":"2952764665210152","nuks":null,"status_kepegawaian":"PPPK","jenis_ptk_id":"3 ","jenis_ptk":"Guru Kelas","pengawas_bidang_studi":"lainnya","agama":"Islam","kewarganegaraan":"ID","alamat_jalan":"SUKOSARI","rt":8,"rw":4,"nama_dusun":"SUKOSARI","desa_kelurahan":"SUKOSARI","kode_kecamatan":"120202  ","kecamatan":"Kec. Kalirejo","kode_kabupaten":"120200  ","kabupaten":"Kab. Lampung Tengah","kode_provinsi":"120000  ","provinsi":"Prov. Lampung","kode_pos":"34174","lintang":null,"bujur":null,"no_telepon_rumah":null,"no_hp":"083160769014","email":"ritawindayani85@gmail.com","status_keaktifan":"Aktif","sk_cpns":null,"tgl_cpns":null,"sk_pengangkatan":"810/431/B.a.VII.01/2022","tmt_pengangkatan":"2022-02-01","lembaga_pengangkat":"Pemerintah Kab/Kota","pangkat_golongan":"-","keahlian_laboratorium":"Lainnya","sumber_gaji":"Sekolah","nama_ibu_kandung":"SAINAH","status_perkawinan":"1","nama_suami_istri":"PAMUJI","nip_suami_istri":null,"pekerjaan_suami_istri":99,"tmt_pns":"2022-02-01","sudah_lisensi_kepala_sekolah":"0","jumlah_sekolah_binaan":0,"pernah_diklat_kepengawasan":"0","nm_wp":null,"status_data":0,"karpeg":null,"karpas":null,"mampu_handle_kk":"0","keahlian_braille":"0","keahlian_bhs_isyarat":"0","npwp":null,"bank":null,"rekening_bank":null,"rekening_atas_nama":null,"tahun_ajaran":"2022/2023","nomor_surat_tugas":"810/431/B.a.VII.01/2022","tanggal_surat_tugas":"2022-02-01","tmt_tugas":"2022-02-01","ptk_induk":"1","jenis_keluar":null,"tgl_ptk_keluar":null,"riwayat_kepangkatan_pangkat_golongan":null,"riwayat_kepangkatan_nomor_sk":null,"riwayat_kepangkatan_tanggal_sk":null,"riwayat_kepangkatan_tmt_pangkat":null,"riwayat_kepangkatan_masa_kerja_gol_tahun":null,"riwayat_kepangkatan_masa_kerja_gol_bulan":null,"riwayat_gaji_berkala_pangkat_golongan":null,"riwayat_gaji_berkala_nomor_sk":null,"riwayat_gaji_berkala_tanggal_sk":null,"riwayat_gaji_berkala_tmt_kgb":null,"riwayat_gaji_berkala_masa_kerja_tahun":null,"riwayat_gaji_berkala_masa_kerja_bulan":null,"riwayat_gaji_berkala_gaji_pokok":null,"inpassing_pangkat_golongan":null,"inpassing_no_sk_inpassing":null,"inpassing_tgl_sk_inpassing":null,"inpassing_tmt_inpassing":null,"inpassing_angka_kredit":null,"inpassing_masa_kerja_tahun":null,"inpassing_masa_kerja_bulan":null,"riwayat_sertifikasi_bidang_studi":null,"riwayat_sertifikasi_jenis_sertifikasi":null,"riwayat_sertifikasi_tahun_sertifikasi":null,"riwayat_sertifikasi_nomor_sertifikat":null,"riwayat_sertifikasi_nrg":null,"riwayat_sertifikasi_nomor_peserta":null,"riwayat_pendidikan_formal_bidang_studi":"Guru Kelas SD/MI","riwayat_pendidikan_formal_jenjang_pendidikan":"S1","riwayat_pendidikan_formal_gelar_akademik":"Sarjana Pendidikan","riwayat_pendidikan_formal_satuan_pendidikan_formal":"","riwayat_pendidikan_formal_fakultas":"","riwayat_pendidikan_formal_kependidikan":"Tidak","riwayat_pendidikan_formal_tahun_masuk":2007,"riwayat_pendidikan_formal_tahun_lulus":2012,"riwayat_pendidikan_formal_nim":"814754559","riwayat_pendidikan_formal_status_kuliah":"Tidak","riwayat_pendidikan_formal_semester":0,"riwayat_pendidikan_formal_ipk":275.0,"jumlah_anak":1,"tugas_tambahan_jabatan_ptk":null,"tugas_tambahan_sekolah":null,"tugas_tambahan_jumlah_jam":null,"tugas_tambahan_nomor_sk":null,"tugas_tambahan_tmt_tambahan":null,"tugas_tambahan_tst_tambahan":null,"riwayat_struktural_jabatan_ptk":"Guru","riwayat_struktural_sk_struktural":"****","riwayat_struktural_tmt_jabatan":"2007-07-20","riwayat_fungsional_jabatan_fungsional":null,"riwayat_fungsional_sk_jabfung":null,"riwayat_fungsional_tmt_jabatan":null,"create_date":"2018-01-24T11:23:02.553000","last_update":"2022-08-18T21:03:40.797000","soft_delete_ptk_terdaftar":0,"soft_delete_rwy_kepangkatan":null,"soft_delete_riwayat_gaji_berkala":null,"soft_delete_inpassing":null,"soft_delete_rwy_sertifikasi":null,"soft_delete_rwy_pend_formal":0,"soft_delete_tugas_tambahan":null,"soft_delete_rwy_struktural":0,"soft_delete_rwy_fungsional":null},{"ptk_id":"20675079-8b18-e111-9585-95f7ac1fb378","semester_id":"20222","sekolah_id":"5027f66f-8b18-e111-bae6-1bd53619789e","ptk_terdaftar_id":"36a18206-a7fb-4213-9db8-ec4a30ca6c91","nama":"Sudarto","nip":"196305111986031010","jenis_kelamin":"L","tempat_lahir":"SENDANGMULYO","tanggal_lahir":"1963-05-11","nik":"1802221105630002","no_kk":null,"niy_nigk":null,"nuptk":"4843741644200012","nuks":null,"status_kepegawaian":"PNS","jenis_ptk_id":"4 ","jenis_ptk":"Guru Mapel","pengawas_bidang_studi":"lainnya","agama":"Islam","kewarganegaraan":"ID","alamat_jalan":"SENDANGREJO","rt":20,"rw":4,"nama_dusun":"SENDANGREJO","desa_kelurahan":"SENDANGREJO","kode_kecamatan":"120218  ","kecamatan":"Kec. Sendang Agung","kode_kabupaten":"120200  ","kabupaten":"Kab. Lampung Tengah","kode_provinsi":"120000  ","provinsi":"Prov. Lampung","kode_pos":"34174","lintang":null,"bujur":null,"no_telepon_rumah":null,"no_hp":"081379096760","email":"sudartosdn3@gmail.com","status_keaktifan":"Aktif","sk_cpns":"215/UP/1986","tgl_cpns":"1986-03-01","sk_pengangkatan":"215/UP/1986","tmt_pengangkatan":"1986-03-01","lembaga_pengangkat":"Pemerintah Pusat","pangkat_golongan":"-","keahlian_laboratorium":"Lainnya","sumber_gaji":"APBN","nama_ibu_kandung":"JINAH","status_perkawinan":"1","nama_suami_istri":"SURNAWATI","nip_suami_istri":null,"pekerjaan_suami_istri":1,"tmt_pns":"1988-02-01","sudah_lisensi_kepala_sekolah":"0","jumlah_sekolah_binaan":0,"pernah_diklat_kepengawasan":"0","nm_wp":null,"status_data":0,"karpeg":null,"karpas":null,"mampu_handle_kk":"2048","keahlian_braille":"0","keahlian_bhs_isyarat":"0","npwp":"879637981321000","bank":null,"rekening_bank":null,"rekening_atas_nama":null,"tahun_ajaran":"2022/2023","nomor_surat_tugas":"KP140136GUVI4PK1986","tanggal_surat_tugas":"1987-01-02","tmt_tugas":"1987-01-02","ptk_induk":"1","jenis_keluar":null,"tgl_ptk_keluar":null,"riwayat_kepangkatan_pangkat_golongan":"IV/a","riwayat_kepangkatan_nomor_sk":"823.4/3860/11.09/2012","riwayat_kepangkatan_tanggal_sk":"2012-05-08","riwayat_kepangkatan_tmt_pangkat":"2012-04-01","riwayat_kepangkatan_masa_kerja_gol_tahun":0,"riwayat_kepangkatan_masa_kerja_gol_bulan":0,"riwayat_gaji_berkala_pangkat_golongan":"IV/a","riwayat_gaji_berkala_nomor_sk":"823.4/0829/B.a.VII.04/2021","riwayat_gaji_berkala_tanggal_sk":"2021-02-05","riwayat_gaji_berkala_tmt_kgb":"2021-03-01","riwayat_gaji_berkala_masa_kerja_tahun":30,"riwayat_gaji_berkala_masa_kerja_bulan":0,"riwayat_gaji_berkala_gaji_pokok":4847300,"inpassing_pangkat_golongan":null,"inpassing_no_sk_inpassing":null,"inpassing_tgl_sk_inpassing":null,"inpassing_tmt_inpassing":null,"inpassing_angka_kredit":null,"inpassing_masa_kerja_tahun":null,"inpassing_masa_kerja_bulan":null,"riwayat_sertifikasi_bidang_studi":"Pendidikan Jasmani dan Kesehatan","riwayat_sertifikasi_jenis_sertifikasi":"Sertifikasi Pendidik","riwayat_sertifikasi_tahun_sertifikasi":null,"riwayat_sertifikasi_nomor_sertifikat":"1071322003023","riwayat_sertifikasi_nrg":null,"riwayat_sertifikasi_nomor_peserta":"13120222010941","riwayat_pendidikan_formal_bidang_studi":"Pendidikan Jasmani dan Kesehatan","riwayat_pendidikan_formal_jenjang_pendidikan":"S1","riwayat_pendidikan_formal_gelar_akademik":"Sarjana Pendidikan","riwayat_pendidikan_formal_satuan_pendidikan_formal":"","riwayat_pendidikan_formal_fakultas":"","riwayat_pendidikan_formal_kependidikan":"Ya","riwayat_pendidikan_formal_tahun_masuk":2011,"riwayat_pendidikan_formal_tahun_lulus":2013,"riwayat_pendidikan_formal_nim":"2011132002P","riwayat_pendidikan_formal_status_kuliah":"Tidak","riwayat_pendidikan_formal_semester":0,"riwayat_pendidikan_formal_ipk":265.0,"jumlah_anak":2,"tugas_tambahan_jabatan_ptk":"Bendahara BOS","tugas_tambahan_sekolah":"(10801547) SD NEGERI 3 SENDANGREJO","tugas_tambahan_jumlah_jam":0,"tugas_tambahan_nomor_sk":"420/31/C8.Da/VI.01/2017","tugas_tambahan_tmt_tambahan":"2017-05-14","tugas_tambahan_tst_tambahan":null,"riwayat_struktural_jabatan_ptk":"Guru","riwayat_struktural_sk_struktural":"****","riwayat_struktural_tmt_jabatan":"1986-03-01","riwayat_fungsional_jabatan_fungsional":null,"riwayat_fungsional_sk_jabfung":null,"riwayat_fungsional_tmt_jabatan":null,"create_date":"2018-01-24T11:23:02.553000","last_update":"2020-11-02T17:46:33.120000","soft_delete_ptk_terdaftar":0,"soft_delete_rwy_kepangkatan":0,"soft_delete_riwayat_gaji_berkala":0,"soft_delete_inpassing":null,"soft_delete_rwy_sertifikasi":0,"soft_delete_rwy_pend_formal":0,"soft_delete_tugas_tambahan":0,"soft_delete_rwy_struktural":0,"soft_delete_rwy_fungsional":null},{"ptk_id":"2726ac86-5cc4-4d8a-8923-e00e7a327e6a","semester_id":"20222","sekolah_id":"5027f66f-8b18-e111-bae6-1bd53619789e","ptk_terdaftar_id":"21502c5a-06b8-4519-8311-3ced347e3863","nama":"MUFLIKHATU SOLIKHAH","nip":null,"jenis_kelamin":"P","tempat_lahir":"SENDANG MULYO","tanggal_lahir":"1998-08-26","nik":"1802226808980001","no_kk":null,"niy_nigk":null,"nuptk":null,"nuks":null,"status_kepegawaian":"Guru Honor Sekolah","jenis_ptk_id":"4 ","jenis_ptk":"Guru Mapel","pengawas_bidang_studi":null,"agama":"Islam","kewarganegaraan":"ID","alamat_jalan":"sendang mulyo","rt":null,"rw":null,"nama_dusun":null,"desa_kelurahan":"sendang mulyo","kode_kecamatan":"120218  ","kecamatan":"Kec. Sendang Agung","kode_kabupaten":"120200  ","kabupaten":"Kab. Lampung Tengah","kode_provinsi":"120000  ","provinsi":"Prov. Lampung","kode_pos":null,"lintang":null,"bujur":null,"no_telepon_rumah":null,"no_hp":null,"email":"muflikhatus31@gmail.com","status_keaktifan":"Aktif","sk_cpns":null,"tgl_cpns":null,"sk_pengangkatan":"420/022/C.8/D.a.VI.01/2022","tmt_pengangkatan":"2022-03-15","lembaga_pengangkat":"Kepala Sekolah","pangkat_golongan":null,"keahlian_laboratorium":null,"sumber_gaji":"Sekolah","nama_ibu_kandung":"SULIYEM","status_perkawinan":"2","nama_suami_istri":null,"nip_suami_istri":null,"pekerjaan_suami_istri":99,"tmt_pns":null,"sudah_lisensi_kepala_sekolah":"0","jumlah_sekolah_binaan":null,"pernah_diklat_kepengawasan":"0","nm_wp":null,"status_data":null,"karpeg":null,"karpas":null,"mampu_handle_kk":"0","keahlian_braille":"0","keahlian_bhs_isyarat":"0","npwp":null,"bank":null,"rekening_bank":null,"rekening_atas_nama":null,"tahun_ajaran":"2022/2023","nomor_surat_tugas":"420/022/C.8/D.a.VI.01/2022","tanggal_surat_tugas":"2022-03-15","tmt_tugas":"2022-03-15","ptk_induk":"1","jenis_keluar":null,"tgl_ptk_keluar":null,"riwayat_kepangkatan_pangkat_golongan":null,"riwayat_kepangkatan_nomor_sk":null,"riwayat_kepangkatan_tanggal_sk":null,"riwayat_kepangkatan_tmt_pangkat":null,"riwayat_kepangkatan_masa_kerja_gol_tahun":null,"riwayat_kepangkatan_masa_kerja_gol_bulan":null,"riwayat_gaji_berkala_pangkat_golongan":null,"riwayat_gaji_berkala_nomor_sk":null,"riwayat_gaji_berkala_tanggal_sk":null,"riwayat_gaji_berkala_tmt_kgb":null,"riwayat_gaji_berkala_masa_kerja_tahun":null,"riwayat_gaji_berkala_masa_kerja_bulan":null,"riwayat_gaji_berkala_gaji_pokok":null,"inpassing_pangkat_golongan":null,"inpassing_no_sk_inpassing":null,"inpassing_tgl_sk_inpassing":null,"inpassing_tmt_inpassing":null,"inpassing_angka_kredit":null,"inpassing_masa_kerja_tahun":null,"inpassing_masa_kerja_bulan":null,"riwayat_sertifikasi_bidang_studi":null,"riwayat_sertifikasi_jenis_sertifikasi":null,"riwayat_sertifikasi_tahun_sertifikasi":null,"riwayat_sertifikasi_nomor_sertifikat":null,"riwayat_sertifikasi_nrg":null,"riwayat_sertifikasi_nomor_peserta":null,"riwayat_pendidikan_formal_bidang_studi":null,"riwayat_pendidikan_formal_jenjang_pendidikan":null,"riwayat_pendidikan_formal_gelar_akademik":null,"riwayat_pendidikan_formal_satuan_pendidikan_formal":null,"riwayat_pendidikan_formal_fakultas":null,"riwayat_pendidikan_formal_kependidikan":null,"riwayat_pendidikan_formal_tahun_masuk":null,"riwayat_pendidikan_formal_tahun_lulus":null,"riwayat_pendidikan_formal_nim":null,"riwayat_pendidikan_formal_status_kuliah":null,"riwayat_pendidikan_formal_semester":null,"riwayat_pendidikan_formal_ipk":null,"jumlah_anak":null,"tugas_tambahan_jabatan_ptk":null,"tugas_tambahan_sekolah":null,"tugas_tambahan_jumlah_jam":null,"tugas_tambahan_nomor_sk":null,"tugas_tambahan_tmt_tambahan":null,"tugas_tambahan_tst_tambahan":null,"riwayat_struktural_jabatan_ptk":null,"riwayat_struktural_sk_struktural":null,"riwayat_struktural_tmt_jabatan":null,"riwayat_fungsional_jabatan_fungsional":null,"riwayat_fungsional_sk_jabfung":null,"riwayat_fungsional_tmt_jabatan":null,"create_date":"2022-04-10T08:59:36.707000","last_update":"2022-04-11T09:29:39.207000","soft_delete_ptk_terdaftar":0,"soft_delete_rwy_kepangkatan":null,"soft_delete_riwayat_gaji_berkala":null,"soft_delete_inpassing":null,"soft_delete_rwy_sertifikasi":null,"soft_delete_rwy_pend_formal":null,"soft_delete_tugas_tambahan":null,"soft_delete_rwy_struktural":null,"soft_delete_rwy_fungsional":null},{"ptk_id":"00648069-ea94-4742-9061-6f3c038de3ea","semester_id":"20222","sekolah_id":"5027f66f-8b18-e111-bae6-1bd53619789e","ptk_terdaftar_id":"0bdb3728-8bcc-4f11-94ea-1c1fe7e1951b","nama":"ADI WIJAYANTO","nip":null,"jenis_kelamin":"L","tempat_lahir":"SENDANG REJO","tanggal_lahir":"2000-12-14","nik":"1802221412000007","no_kk":null,"niy_nigk":null,"nuptk":null,"nuks":null,"status_kepegawaian":"Tenaga Honor Sekolah","jenis_ptk_id":"6 ","jenis_ptk":"Guru Pendamping Khusus","pengawas_bidang_studi":null,"agama":"Islam","kewarganegaraan":"ID","alamat_jalan":"sendang mulyo","rt":null,"rw":null,"nama_dusun":null,"desa_kelurahan":"sendang mulyo","kode_kecamatan":"120218  ","kecamatan":"Kec. Sendang Agung","kode_kabupaten":"120200  ","kabupaten":"Kab. Lampung Tengah","kode_provinsi":"120000  ","provinsi":"Prov. Lampung","kode_pos":null,"lintang":null,"bujur":null,"no_telepon_rumah":null,"no_hp":null,"email":"wijayantoadi157@gmail.com","status_keaktifan":"Aktif","sk_cpns":null,"tgl_cpns":null,"sk_pengangkatan":"420/021/C.8/D.a.VI.01/2022","tmt_pengangkatan":"2022-03-22","lembaga_pengangkat":"Kepala Sekolah","pangkat_golongan":null,"keahlian_laboratorium":null,"sumber_gaji":"Sekolah","nama_ibu_kandung":"MURSITI","status_perkawinan":"2","nama_suami_istri":null,"nip_suami_istri":null,"pekerjaan_suami_istri":99,"tmt_pns":null,"sudah_lisensi_kepala_sekolah":"0","jumlah_sekolah_binaan":null,"pernah_diklat_kepengawasan":"0","nm_wp":null,"status_data":null,"karpeg":null,"karpas":null,"mampu_handle_kk":"0","keahlian_braille":"0","keahlian_bhs_isyarat":"0","npwp":null,"bank":null,"rekening_bank":null,"rekening_atas_nama":null,"tahun_ajaran":"2022/2023","nomor_surat_tugas":"420/021/C.8/D.a.VI.01/2022","tanggal_surat_tugas":"2022-03-22","tmt_tugas":"2022-03-22","ptk_induk":"1","jenis_keluar":null,"tgl_ptk_keluar":null,"riwayat_kepangkatan_pangkat_golongan":null,"riwayat_kepangkatan_nomor_sk":null,"riwayat_kepangkatan_tanggal_sk":null,"riwayat_kepangkatan_tmt_pangkat":null,"riwayat_kepangkatan_masa_kerja_gol_tahun":null,"riwayat_kepangkatan_masa_kerja_gol_bulan":null,"riwayat_gaji_berkala_pangkat_golongan":null,"riwayat_gaji_berkala_nomor_sk":null,"riwayat_gaji_berkala_tanggal_sk":null,"riwayat_gaji_berkala_tmt_kgb":null,"riwayat_gaji_berkala_masa_kerja_tahun":null,"riwayat_gaji_berkala_masa_kerja_bulan":null,"riwayat_gaji_berkala_gaji_pokok":null,"inpassing_pangkat_golongan":null,"inpassing_no_sk_inpassing":null,"inpassing_tgl_sk_inpassing":null,"inpassing_tmt_inpassing":null,"inpassing_angka_kredit":null,"inpassing_masa_kerja_tahun":null,"inpassing_masa_kerja_bulan":null,"riwayat_sertifikasi_bidang_studi":null,"riwayat_sertifikasi_jenis_sertifikasi":null,"riwayat_sertifikasi_tahun_sertifikasi":null,"riwayat_sertifikasi_nomor_sertifikat":null,"riwayat_sertifikasi_nrg":null,"riwayat_sertifikasi_nomor_peserta":null,"riwayat_pendidikan_formal_bidang_studi":null,"riwayat_pendidikan_formal_jenjang_pendidikan":null,"riwayat_pendidikan_formal_gelar_akademik":null,"riwayat_pendidikan_formal_satuan_pendidikan_formal":null,"riwayat_pendidikan_formal_fakultas":null,"riwayat_pendidikan_formal_kependidikan":null,"riwayat_pendidikan_formal_tahun_masuk":null,"riwayat_pendidikan_formal_tahun_lulus":null,"riwayat_pendidikan_formal_nim":null,"riwayat_pendidikan_formal_status_kuliah":null,"riwayat_pendidikan_formal_semester":null,"riwayat_pendidikan_formal_ipk":null,"jumlah_anak":null,"tugas_tambahan_jabatan_ptk":null,"tugas_tambahan_sekolah":null,"tugas_tambahan_jumlah_jam":null,"tugas_tambahan_nomor_sk":null,"tugas_tambahan_tmt_tambahan":null,"tugas_tambahan_tst_tambahan":null,"riwayat_struktural_jabatan_ptk":null,"riwayat_struktural_sk_struktural":null,"riwayat_struktural_tmt_jabatan":null,"riwayat_fungsional_jabatan_fungsional":null,"riwayat_fungsional_sk_jabfung":null,"riwayat_fungsional_tmt_jabatan":null,"create_date":"2022-04-10T08:59:36.707000","last_update":"2022-04-11T09:29:39.207000","soft_delete_ptk_terdaftar":0,"soft_delete_rwy_kepangkatan":null,"soft_delete_riwayat_gaji_berkala":null,"soft_delete_inpassing":null,"soft_delete_rwy_sertifikasi":null,"soft_delete_rwy_pend_formal":null,"soft_delete_tugas_tambahan":null,"soft_delete_rwy_struktural":null,"soft_delete_rwy_fungsional":null},{"ptk_id":"9d29d83d-8256-e211-a52e-174dfb3219c8","semester_id":"20222","sekolah_id":"5027f66f-8b18-e111-bae6-1bd53619789e","ptk_terdaftar_id":"e80f32d8-4f52-4fe5-adf1-5c5b6c724b9e","nama":"Maryusup","nip":"196201171982031003","jenis_kelamin":"L","tempat_lahir":"SENDANGAGUNG","tanggal_lahir":"1962-01-17","nik":"1802221701620017","no_kk":null,"niy_nigk":null,"nuptk":"3449740641200002","nuks":null,"status_kepegawaian":"PNS","jenis_ptk_id":"3 ","jenis_ptk":"Guru Kelas","pengawas_bidang_studi":"lainnya","agama":"Islam","kewarganegaraan":"ID","alamat_jalan":"SENDANGAGUNG","rt":12,"rw":6,"nama_dusun":"SENDANGAGUNG","desa_kelurahan":"SENDANGAGUNG","kode_kecamatan":"120218  ","kecamatan":"Kec. Sendang Agung","kode_kabupaten":"120200  ","kabupaten":"Kab. Lampung Tengah","kode_provinsi":"120000  ","provinsi":"Prov. Lampung","kode_pos":"34174","lintang":null,"bujur":null,"no_telepon_rumah":null,"no_hp":"085758499044","email":"maryusupspd@gmail.com","status_keaktifan":"Aktif","sk_cpns":"600/UP/1982","tgl_cpns":"1982-03-01","sk_pengangkatan":"600/UP/1982","tmt_pengangkatan":"1982-03-01","lembaga_pengangkat":"Pemerintah Pusat","pangkat_golongan":"-","keahlian_laboratorium":"Lainnya","sumber_gaji":"APBN","nama_ibu_kandung":"PAYADIYAH","status_perkawinan":"1","nama_suami_istri":"MUKSODAH","nip_suami_istri":"196111051984032012","pekerjaan_suami_istri":5,"tmt_pns":"1984-04-01","sudah_lisensi_kepala_sekolah":"0","jumlah_sekolah_binaan":0,"pernah_diklat_kepengawasan":"0","nm_wp":null,"status_data":0,"karpeg":null,"karpas":null,"mampu_handle_kk":"2048","keahlian_braille":"0","keahlian_bhs_isyarat":"0","npwp":"879637932321000","bank":null,"rekening_bank":null,"rekening_atas_nama":null,"tahun_ajaran":"2022/2023","nomor_surat_tugas":"KP140709GUVI3PDK1982","tanggal_surat_tugas":"1982-02-27","tmt_tugas":"1982-03-01","ptk_induk":"0","jenis_keluar":"Pensiun","tgl_ptk_keluar":"2022-02-01","riwayat_kepangkatan_pangkat_golongan":"IV/a","riwayat_kepangkatan_nomor_sk":"823.4/1070/11.12/2008","riwayat_kepangkatan_tanggal_sk":"2008-04-25","riwayat_kepangkatan_tmt_pangkat":"2008-04-01","riwayat_kepangkatan_masa_kerja_gol_tahun":0,"riwayat_kepangkatan_masa_kerja_gol_bulan":0,"riwayat_gaji_berkala_pangkat_golongan":"IV/a","riwayat_gaji_berkala_nomor_sk":"823.4/1424/B.a.VII.04/2019","riwayat_gaji_berkala_tanggal_sk":"2019-01-02","riwayat_gaji_berkala_tmt_kgb":"2019-03-01","riwayat_gaji_berkala_masa_kerja_tahun":32,"riwayat_gaji_berkala_masa_kerja_bulan":0,"riwayat_gaji_berkala_gaji_pokok":4762000,"inpassing_pangkat_golongan":null,"inpassing_no_sk_inpassing":null,"inpassing_tgl_sk_inpassing":null,"inpassing_tmt_inpassing":null,"inpassing_angka_kredit":null,"inpassing_masa_kerja_tahun":null,"inpassing_masa_kerja_bulan":null,"riwayat_sertifikasi_bidang_studi":"Guru Kelas SD/MI","riwayat_sertifikasi_jenis_sertifikasi":"Sertifikasi Pendidik","riwayat_sertifikasi_tahun_sertifikasi":null,"riwayat_sertifikasi_nomor_sertifikat":"10711102702336","riwayat_sertifikasi_nrg":null,"riwayat_sertifikasi_nomor_peserta":"11120202710586","riwayat_pendidikan_formal_bidang_studi":null,"riwayat_pendidikan_formal_jenjang_pendidikan":null,"riwayat_pendidikan_formal_gelar_akademik":null,"riwayat_pendidikan_formal_satuan_pendidikan_formal":null,"riwayat_pendidikan_formal_fakultas":null,"riwayat_pendidikan_formal_kependidikan":null,"riwayat_pendidikan_formal_tahun_masuk":null,"riwayat_pendidikan_formal_tahun_lulus":null,"riwayat_pendidikan_formal_nim":null,"riwayat_pendidikan_formal_status_kuliah":null,"riwayat_pendidikan_formal_semester":null,"riwayat_pendidikan_formal_ipk":null,"jumlah_anak":2,"tugas_tambahan_jabatan_ptk":null,"tugas_tambahan_sekolah":null,"tugas_tambahan_jumlah_jam":null,"tugas_tambahan_nomor_sk":null,"tugas_tambahan_tmt_tambahan":null,"tugas_tambahan_tst_tambahan":null,"riwayat_struktural_jabatan_ptk":"Guru","riwayat_struktural_sk_struktural":"****","riwayat_struktural_tmt_jabatan":"1982-03-01","riwayat_fungsional_jabatan_fungsional":null,"riwayat_fungsional_sk_jabfung":null,"riwayat_fungsional_tmt_jabatan":null,"create_date":"2018-01-24T11:23:02.553000","last_update":"2020-11-02T17:46:33.120000","soft_delete_ptk_terdaftar":0,"soft_delete_rwy_kepangkatan":0,"soft_delete_riwayat_gaji_berkala":0,"soft_delete_inpassing":null,"soft_delete_rwy_sertifikasi":0,"soft_delete_rwy_pend_formal":null,"soft_delete_tugas_tambahan":null,"soft_delete_rwy_struktural":0,"soft_delete_rwy_fungsional":null},{"ptk_id":"60305079-8b18-e111-9436-81329b65719b","semester_id":"20222","sekolah_id":"5027f66f-8b18-e111-bae6-1bd53619789e","ptk_terdaftar_id":"0d98b085-9a80-41b7-9246-58dc293e572f","nama":"Muksodah","nip":"196111051984032012","jenis_kelamin":"P","tempat_lahir":"SINARWAYA","tanggal_lahir":"1961-11-05","nik":"1802224511610001","no_kk":null,"niy_nigk":null,"nuptk":"6447739641300003","nuks":null,"status_kepegawaian":"PNS","jenis_ptk_id":"3 ","jenis_ptk":"Guru Kelas","pengawas_bidang_studi":"lainnya","agama":"Islam","kewarganegaraan":"ID","alamat_jalan":"sendangagung","rt":12,"rw":6,"nama_dusun":"SENDANGAGUNG","desa_kelurahan":"SENDANGAGUNG","kode_kecamatan":"120218  ","kecamatan":"Kec. Sendang Agung","kode_kabupaten":"120200  ","kabupaten":"Kab. Lampung Tengah","kode_provinsi":"120000  ","provinsi":"Prov. Lampung","kode_pos":"34174","lintang":null,"bujur":null,"no_telepon_rumah":null,"no_hp":"085709785797","email":"muksodah1961@gmail.com","status_keaktifan":"Aktif","sk_cpns":"732/UP/1984","tgl_cpns":"1984-03-01","sk_pengangkatan":"732/UP/1984","tmt_pengangkatan":"1984-03-01","lembaga_pengangkat":"Pemerintah Pusat","pangkat_golongan":"IV/a","keahlian_laboratorium":"Lainnya","sumber_gaji":"APBN","nama_ibu_kandung":"HASNAH","status_perkawinan":"1","nama_suami_istri":"MARYUSUP","nip_suami_istri":"196201171982031003","pekerjaan_suami_istri":5,"tmt_pns":"1986-03-01","sudah_lisensi_kepala_sekolah":"0","jumlah_sekolah_binaan":0,"pernah_diklat_kepengawasan":"0","nm_wp":null,"status_data":0,"karpeg":null,"karpas":null,"mampu_handle_kk":"0","keahlian_braille":"0","keahlian_bhs_isyarat":"0","npwp":"879637973321000","bank":null,"rekening_bank":null,"rekening_atas_nama":null,"tahun_ajaran":"2022/2023","nomor_surat_tugas":"KP14007IV4PK1984","tanggal_surat_tugas":"1985-03-01","tmt_tugas":"1984-10-01","ptk_induk":"0","jenis_keluar":"Pensiun","tgl_ptk_keluar":"2021-12-01","riwayat_kepangkatan_pangkat_golongan":"IV/a","riwayat_kepangkatan_nomor_sk":"823.4/882/11.12/2009","riwayat_kepangkatan_tanggal_sk":"2009-04-01","riwayat_kepangkatan_tmt_pangkat":"2009-04-01","riwayat_kepangkatan_masa_kerja_gol_tahun":0,"riwayat_kepangkatan_masa_kerja_gol_bulan":0,"riwayat_gaji_berkala_pangkat_golongan":"IV/a","riwayat_gaji_berkala_nomor_sk":"823.4/0739/B.a.VII.04/2021","riwayat_gaji_berkala_tanggal_sk":"2021-02-05","riwayat_gaji_berkala_tmt_kgb":"2021-03-01","riwayat_gaji_berkala_masa_kerja_tahun":32,"riwayat_gaji_berkala_masa_kerja_bulan":0,"riwayat_gaji_berkala_gaji_pokok":5000000,"inpassing_pangkat_golongan":null,"inpassing_no_sk_inpassing":null,"inpassing_tgl_sk_inpassing":null,"inpassing_tmt_inpassing":null,"inpassing_angka_kredit":null,"inpassing_masa_kerja_tahun":null,"inpassing_masa_kerja_bulan":null,"riwayat_sertifikasi_bidang_studi":"Guru Kelas SD/MI","riwayat_sertifikasi_jenis_sertifikasi":"Sertifikasi Pendidik","riwayat_sertifikasi_tahun_sertifikasi":null,"riwayat_sertifikasi_nomor_sertifikat":"1071102702767","riwayat_sertifikasi_nrg":null,"riwayat_sertifikasi_nomor_peserta":"11120202710990","riwayat_pendidikan_formal_bidang_studi":"Guru Kelas SD/MI","riwayat_pendidikan_formal_jenjang_pendidikan":"S1","riwayat_pendidikan_formal_gelar_akademik":"Sarjana Pendidikan","riwayat_pendidikan_formal_satuan_pendidikan_formal":"","riwayat_pendidikan_formal_fakultas":"","riwayat_pendidikan_formal_kependidikan":"Ya","riwayat_pendidikan_formal_tahun_masuk":0,"riwayat_pendidikan_formal_tahun_lulus":2015,"riwayat_pendidikan_formal_nim":"tidak diisi","riwayat_pendidikan_formal_status_kuliah":"Tidak","riwayat_pendidikan_formal_semester":0,"riwayat_pendidikan_formal_ipk":0.0,"jumlah_anak":null,"tugas_tambahan_jabatan_ptk":null,"tugas_tambahan_sekolah":null,"tugas_tambahan_jumlah_jam":null,"tugas_tambahan_nomor_sk":null,"tugas_tambahan_tmt_tambahan":null,"tugas_tambahan_tst_tambahan":null,"riwayat_struktural_jabatan_ptk":"Guru","riwayat_struktural_sk_struktural":"****","riwayat_struktural_tmt_jabatan":"1984-03-01","riwayat_fungsional_jabatan_fungsional":null,"riwayat_fungsional_sk_jabfung":null,"riwayat_fungsional_tmt_jabatan":null,"create_date":"2018-01-24T11:23:02.553000","last_update":"2020-11-02T17:46:33.120000","soft_delete_ptk_terdaftar":0,"soft_delete_rwy_kepangkatan":0,"soft_delete_riwayat_gaji_berkala":0,"soft_delete_inpassing":null,"soft_delete_rwy_sertifikasi":0,"soft_delete_rwy_pend_formal":0,"soft_delete_tugas_tambahan":null,"soft_delete_rwy_struktural":0,"soft_delete_rwy_fungsional":null},{"ptk_id":"904c5079-8b18-e111-b030-71c121ba27c0","semester_id":"20222","sekolah_id":"5027f66f-8b18-e111-bae6-1bd53619789e","ptk_terdaftar_id":"53b54b20-9af5-485f-83ff-fc43c714bf7d","nama":"Solikhin","nip":"196203141984031006","jenis_kelamin":"L","tempat_lahir":"CILACAP","tanggal_lahir":"1962-03-14","nik":"1802221403620002","no_kk":null,"niy_nigk":"1802221403620002","nuptk":"7646740642200022","nuks":null,"status_kepegawaian":"PNS","jenis_ptk_id":"4 ","jenis_ptk":"Guru Mapel","pengawas_bidang_studi":"lainnya","agama":"Islam","kewarganegaraan":"ID","alamat_jalan":"SENDANGMULYO","rt":2,"rw":2,"nama_dusun":"SENDANGMULYO","desa_kelurahan":"SENDANGMULYO","kode_kecamatan":"120218  ","kecamatan":"Kec. Sendang Agung","kode_kabupaten":"120200  ","kabupaten":"Kab. Lampung Tengah","kode_provinsi":"120000  ","provinsi":"Prov. Lampung","kode_pos":"34174","lintang":null,"bujur":null,"no_telepon_rumah":null,"no_hp":"087894190240","email":"solikhinspdi62@gmail.com","status_keaktifan":"Aktif","sk_cpns":"736/UP/1984","tgl_cpns":"1984-01-03","sk_pengangkatan":"736/UP/1984","tmt_pengangkatan":"1984-03-01","lembaga_pengangkat":"Pemerintah Pusat","pangkat_golongan":"IV/a","keahlian_laboratorium":"Lainnya","sumber_gaji":"Lainnya","nama_ibu_kandung":"KARTEM","status_perkawinan":"1","nama_suami_istri":"SULIYEM","nip_suami_istri":"1963050819850320  ","pekerjaan_suami_istri":5,"tmt_pns":"1984-10-01","sudah_lisensi_kepala_sekolah":"0","jumlah_sekolah_binaan":0,"pernah_diklat_kepengawasan":"0","nm_wp":null,"status_data":0,"karpeg":null,"karpas":null,"mampu_handle_kk":"0","keahlian_braille":"0","keahlian_bhs_isyarat":"0","npwp":"872460407321000","bank":null,"rekening_bank":null,"rekening_atas_nama":null,"tahun_ajaran":"2022/2023","nomor_surat_tugas":"KP14068GAVII4PK1984","tanggal_surat_tugas":"1984-01-10","tmt_tugas":"1984-03-01","ptk_induk":"0","jenis_keluar":"Pensiun","tgl_ptk_keluar":"2022-02-10","riwayat_kepangkatan_pangkat_golongan":"IV/b","riwayat_kepangkatan_nomor_sk":"823.4/0078/B.a.VII.04/2019","riwayat_kepangkatan_tanggal_sk":"2019-01-02","riwayat_kepangkatan_tmt_pangkat":"2019-03-01","riwayat_kepangkatan_masa_kerja_gol_tahun":30,"riwayat_kepangkatan_masa_kerja_gol_bulan":0,"riwayat_gaji_berkala_pangkat_golongan":"IV/a","riwayat_gaji_berkala_nomor_sk":"823.4/0097/B.a.VII.04/2021","riwayat_gaji_berkala_tanggal_sk":"2021-01-04","riwayat_gaji_berkala_tmt_kgb":"2021-03-01","riwayat_gaji_berkala_masa_kerja_tahun":32,"riwayat_gaji_berkala_masa_kerja_bulan":0,"riwayat_gaji_berkala_gaji_pokok":5211500,"inpassing_pangkat_golongan":null,"inpassing_no_sk_inpassing":null,"inpassing_tgl_sk_inpassing":null,"inpassing_tmt_inpassing":null,"inpassing_angka_kredit":null,"inpassing_masa_kerja_tahun":null,"inpassing_masa_kerja_bulan":null,"riwayat_sertifikasi_bidang_studi":"Pendidikan Agama Islam","riwayat_sertifikasi_jenis_sertifikasi":"Sertifikasi Pendidik","riwayat_sertifikasi_tahun_sertifikasi":null,"riwayat_sertifikasi_nomor_sertifikat":"7646-7406-4220-0022","riwayat_sertifikasi_nrg":null,"riwayat_sertifikasi_nomor_peserta":"11120212720222","riwayat_pendidikan_formal_bidang_studi":null,"riwayat_pendidikan_formal_jenjang_pendidikan":null,"riwayat_pendidikan_formal_gelar_akademik":null,"riwayat_pendidikan_formal_satuan_pendidikan_formal":null,"riwayat_pendidikan_formal_fakultas":null,"riwayat_pendidikan_formal_kependidikan":null,"riwayat_pendidikan_formal_tahun_masuk":null,"riwayat_pendidikan_formal_tahun_lulus":null,"riwayat_pendidikan_formal_nim":null,"riwayat_pendidikan_formal_status_kuliah":null,"riwayat_pendidikan_formal_semester":null,"riwayat_pendidikan_formal_ipk":null,"jumlah_anak":3,"tugas_tambahan_jabatan_ptk":null,"tugas_tambahan_sekolah":null,"tugas_tambahan_jumlah_jam":null,"tugas_tambahan_nomor_sk":null,"tugas_tambahan_tmt_tambahan":null,"tugas_tambahan_tst_tambahan":null,"riwayat_struktural_jabatan_ptk":"Guru","riwayat_struktural_sk_struktural":"****","riwayat_struktural_tmt_jabatan":"1984-03-01","riwayat_fungsional_jabatan_fungsional":null,"riwayat_fungsional_sk_jabfung":null,"riwayat_fungsional_tmt_jabatan":null,"create_date":"2018-01-24T11:23:02.553000","last_update":"2020-11-02T17:46:33.120000","soft_delete_ptk_terdaftar":0,"soft_delete_rwy_kepangkatan":0,"soft_delete_riwayat_gaji_berkala":0,"soft_delete_inpassing":null,"soft_delete_rwy_sertifikasi":0,"soft_delete_rwy_pend_formal":null,"soft_delete_tugas_tambahan":null,"soft_delete_rwy_struktural":0,"soft_delete_rwy_fungsional":null}]