[{"ptk_id":"b53e3123-ae07-e211-a8e5-df0543f6e3e9","semester_id":"20222","sekolah_id":"c09cc86f-8b18-e111-b090-314ae660b182","ptk_terdaftar_id":"60a0a4ca-09d7-4f2f-8655-d6e968b272aa","nama":"Ny Sumetrra","nip":"196304131985031004","jenis_kelamin":"L","tempat_lahir":"LAMPUNG","tanggal_lahir":"1963-04-13","nik":"1802080103630003","no_kk":null,"niy_nigk":null,"nuptk":"4745741644200002","nuks":null,"status_kepegawaian":"PNS","jenis_ptk_id":"20","jenis_ptk":"Kepala Sekolah","pengawas_bidang_studi":"lainnya","agama":"Hindu","kewarganegaraan":"ID","alamat_jalan":"RAMA OETAMA","rt":1,"rw":2,"nama_dusun":null,"desa_kelurahan":"RAMA OETAMA","kode_kecamatan":"120207  ","kecamatan":"Kec. Seputih Raman","kode_kabupaten":"120200  ","kabupaten":"Kab. Lampung Tengah","kode_provinsi":"120000  ","provinsi":"Prov. Lampung","kode_pos":"34155","lintang":null,"bujur":null,"no_telepon_rumah":null,"no_hp":"081272629300","email":"nysumetrra@gmail.com","status_keaktifan":"Aktif","sk_cpns":"270/UP/1985","tgl_cpns":"1985-03-01","sk_pengangkatan":"270/UP/1985","tmt_pengangkatan":"1985-03-01","lembaga_pengangkat":"Pemerintah Pusat","pangkat_golongan":"IV/a","keahlian_laboratorium":"Lainnya","sumber_gaji":"APBD Kabupaten/Kota","nama_ibu_kandung":"MEN MAWA ALM","status_perkawinan":"1","nama_suami_istri":"NI MADE SINIASIH","nip_suami_istri":null,"pekerjaan_suami_istri":9,"tmt_pns":"1986-10-01","sudah_lisensi_kepala_sekolah":"0","jumlah_sekolah_binaan":0,"pernah_diklat_kepengawasan":"0","nm_wp":null,"status_data":0,"karpeg":null,"karpas":null,"mampu_handle_kk":"0","keahlian_braille":"0","keahlian_bhs_isyarat":"0","npwp":"675536338321000","bank":null,"rekening_bank":null,"rekening_atas_nama":null,"tahun_ajaran":"2022/2023","nomor_surat_tugas":"Kp.140/72/GO/VI/4/85","tanggal_surat_tugas":"1985-08-31","tmt_tugas":"1985-09-02","ptk_induk":"1","jenis_keluar":null,"tgl_ptk_keluar":null,"riwayat_kepangkatan_pangkat_golongan":"IV/b","riwayat_kepangkatan_nomor_sk":"823.4/785.1/VI.04/2018","riwayat_kepangkatan_tanggal_sk":"2018-10-22","riwayat_kepangkatan_tmt_pangkat":"2018-10-01","riwayat_kepangkatan_masa_kerja_gol_tahun":28,"riwayat_kepangkatan_masa_kerja_gol_bulan":7,"riwayat_gaji_berkala_pangkat_golongan":"IV/b","riwayat_gaji_berkala_nomor_sk":"823.4/0066/B.a.VII.04/2022","riwayat_gaji_berkala_tanggal_sk":"2022-01-12","riwayat_gaji_berkala_tmt_kgb":"2022-03-01","riwayat_gaji_berkala_masa_kerja_tahun":32,"riwayat_gaji_berkala_masa_kerja_bulan":0,"riwayat_gaji_berkala_gaji_pokok":5211500,"inpassing_pangkat_golongan":"III/b","inpassing_no_sk_inpassing":"808/355/LTD.5/2003","inpassing_tgl_sk_inpassing":null,"inpassing_tmt_inpassing":"2003-01-01","inpassing_angka_kredit":0,"inpassing_masa_kerja_tahun":12,"inpassing_masa_kerja_bulan":10,"riwayat_sertifikasi_bidang_studi":"Pendidikan Jasmani dan Kesehatan","riwayat_sertifikasi_jenis_sertifikasi":"Sertifikasi Pendidik","riwayat_sertifikasi_tahun_sertifikasi":null,"riwayat_sertifikasi_nomor_sertifikat":"1071222004666","riwayat_sertifikasi_nrg":null,"riwayat_sertifikasi_nomor_peserta":"12120222010896","riwayat_pendidikan_formal_bidang_studi":null,"riwayat_pendidikan_formal_jenjang_pendidikan":null,"riwayat_pendidikan_formal_gelar_akademik":null,"riwayat_pendidikan_formal_satuan_pendidikan_formal":null,"riwayat_pendidikan_formal_fakultas":null,"riwayat_pendidikan_formal_kependidikan":null,"riwayat_pendidikan_formal_tahun_masuk":null,"riwayat_pendidikan_formal_tahun_lulus":null,"riwayat_pendidikan_formal_nim":null,"riwayat_pendidikan_formal_status_kuliah":null,"riwayat_pendidikan_formal_semester":null,"riwayat_pendidikan_formal_ipk":null,"jumlah_anak":3,"tugas_tambahan_jabatan_ptk":"Kepala Sekolah","tugas_tambahan_sekolah":"(10802534) SD NEGERI 2 RAMA DEWA","tugas_tambahan_jumlah_jam":0,"tugas_tambahan_nomor_sk":"821.29/891/B.a.VII.04/2021","tugas_tambahan_tmt_tambahan":"2021-12-14","tugas_tambahan_tst_tambahan":null,"riwayat_struktural_jabatan_ptk":"Guru","riwayat_struktural_sk_struktural":"****","riwayat_struktural_tmt_jabatan":"1985-03-01","riwayat_fungsional_jabatan_fungsional":null,"riwayat_fungsional_sk_jabfung":null,"riwayat_fungsional_tmt_jabatan":null,"create_date":"2018-01-24T11:23:02.553000","last_update":"2022-03-08T21:26:47.243000","soft_delete_ptk_terdaftar":0,"soft_delete_rwy_kepangkatan":0,"soft_delete_riwayat_gaji_berkala":0,"soft_delete_inpassing":0,"soft_delete_rwy_sertifikasi":0,"soft_delete_rwy_pend_formal":null,"soft_delete_tugas_tambahan":0,"soft_delete_rwy_struktural":0,"soft_delete_rwy_fungsional":null},{"ptk_id":"9da92a1b-4ffd-e111-af34-17fe3b467b82","semester_id":"20222","sekolah_id":"c09cc86f-8b18-e111-b090-314ae660b182","ptk_terdaftar_id":"597dd2f0-d5f6-46e4-8886-e88e3b1640b5","nama":"Ni Wy. Sukendri","nip":"196902062007012019","jenis_kelamin":"P","tempat_lahir":"RAMA DEWA","tanggal_lahir":"1969-02-06","nik":"1802084602690010","no_kk":null,"niy_nigk":null,"nuptk":"3538747649300042","nuks":null,"status_kepegawaian":"PNS","jenis_ptk_id":"3 ","jenis_ptk":"Guru Kelas","pengawas_bidang_studi":"lainnya","agama":"Hindu","kewarganegaraan":"ID","alamat_jalan":"RAMA DEWA 5","rt":6,"rw":5,"nama_dusun":"Dusun 5","desa_kelurahan":"RAMA DEWA","kode_kecamatan":"120207  ","kecamatan":"Kec. Seputih Raman","kode_kabupaten":"120200  ","kabupaten":"Kab. Lampung Tengah","kode_provinsi":"120000  ","provinsi":"Prov. Lampung","kode_pos":"34155","lintang":null,"bujur":null,"no_telepon_rumah":null,"no_hp":"085368424969","email":"wysukendri@gmail.com","status_keaktifan":"Aktif","sk_cpns":"810/385/LTD.4/2007","tgl_cpns":"2007-01-01","sk_pengangkatan":"420/03265/KPTS/D.8/2003","tmt_pengangkatan":"2003-06-01","lembaga_pengangkat":"Pemerintah Pusat","pangkat_golongan":"II/c","keahlian_laboratorium":"Lainnya","sumber_gaji":"APBD Kabupaten/Kota","nama_ibu_kandung":"SEMUTRI","status_perkawinan":"1","nama_suami_istri":"I WY. NURYASA","nip_suami_istri":null,"pekerjaan_suami_istri":9,"tmt_pns":"2009-07-01","sudah_lisensi_kepala_sekolah":"0","jumlah_sekolah_binaan":0,"pernah_diklat_kepengawasan":"0","nm_wp":null,"status_data":0,"karpeg":null,"karpas":null,"mampu_handle_kk":"0","keahlian_braille":"0","keahlian_bhs_isyarat":"0","npwp":null,"bank":null,"rekening_bank":null,"rekening_atas_nama":null,"tahun_ajaran":"2022/2023","nomor_surat_tugas":"821.29/937/01/2010","tanggal_surat_tugas":"2010-05-27","tmt_tugas":"2010-05-27","ptk_induk":"1","jenis_keluar":null,"tgl_ptk_keluar":null,"riwayat_kepangkatan_pangkat_golongan":"III/b","riwayat_kepangkatan_nomor_sk":"823.3/760/B.a.VII.04/04/2020","riwayat_kepangkatan_tanggal_sk":"2020-06-03","riwayat_kepangkatan_tmt_pangkat":"2020-04-01","riwayat_kepangkatan_masa_kerja_gol_tahun":11,"riwayat_kepangkatan_masa_kerja_gol_bulan":10,"riwayat_gaji_berkala_pangkat_golongan":"III/b","riwayat_gaji_berkala_nomor_sk":"823.3/1372/B.a.VII.04/2022","riwayat_gaji_berkala_tanggal_sk":"2022-04-20","riwayat_gaji_berkala_tmt_kgb":"2022-06-01","riwayat_gaji_berkala_masa_kerja_tahun":14,"riwayat_gaji_berkala_masa_kerja_bulan":0,"riwayat_gaji_berkala_gaji_pokok":3340300,"inpassing_pangkat_golongan":null,"inpassing_no_sk_inpassing":null,"inpassing_tgl_sk_inpassing":null,"inpassing_tmt_inpassing":null,"inpassing_angka_kredit":null,"inpassing_masa_kerja_tahun":null,"inpassing_masa_kerja_bulan":null,"riwayat_sertifikasi_bidang_studi":"Guru Kelas SD/MI","riwayat_sertifikasi_jenis_sertifikasi":"Sertifikasi Pendidik","riwayat_sertifikasi_tahun_sertifikasi":null,"riwayat_sertifikasi_nomor_sertifikat":"16120202710307","riwayat_sertifikasi_nrg":null,"riwayat_sertifikasi_nomor_peserta":"16120202710307","riwayat_pendidikan_formal_bidang_studi":null,"riwayat_pendidikan_formal_jenjang_pendidikan":null,"riwayat_pendidikan_formal_gelar_akademik":null,"riwayat_pendidikan_formal_satuan_pendidikan_formal":null,"riwayat_pendidikan_formal_fakultas":null,"riwayat_pendidikan_formal_kependidikan":null,"riwayat_pendidikan_formal_tahun_masuk":null,"riwayat_pendidikan_formal_tahun_lulus":null,"riwayat_pendidikan_formal_nim":null,"riwayat_pendidikan_formal_status_kuliah":null,"riwayat_pendidikan_formal_semester":null,"riwayat_pendidikan_formal_ipk":null,"jumlah_anak":2,"tugas_tambahan_jabatan_ptk":"Bendahara BOS","tugas_tambahan_sekolah":"(10802534) SD NEGERI 2 RAMA DEWA","tugas_tambahan_jumlah_jam":0,"tugas_tambahan_nomor_sk":"900/08/C.10/ D.1/ 2019","tugas_tambahan_tmt_tambahan":"2019-03-07","tugas_tambahan_tst_tambahan":null,"riwayat_struktural_jabatan_ptk":"Guru","riwayat_struktural_sk_struktural":"****","riwayat_struktural_tmt_jabatan":"2007-01-01","riwayat_fungsional_jabatan_fungsional":null,"riwayat_fungsional_sk_jabfung":null,"riwayat_fungsional_tmt_jabatan":null,"create_date":"2018-01-24T11:23:02.553000","last_update":"2020-11-02T17:46:33.120000","soft_delete_ptk_terdaftar":0,"soft_delete_rwy_kepangkatan":0,"soft_delete_riwayat_gaji_berkala":0,"soft_delete_inpassing":null,"soft_delete_rwy_sertifikasi":0,"soft_delete_rwy_pend_formal":null,"soft_delete_tugas_tambahan":0,"soft_delete_rwy_struktural":0,"soft_delete_rwy_fungsional":null},{"ptk_id":"7eabf39b-9049-485c-805c-57262e2ba7f2","semester_id":"20222","sekolah_id":"c09cc86f-8b18-e111-b090-314ae660b182","ptk_terdaftar_id":"bd2f512f-205f-4345-98e6-bf0548183cf0","nama":"Margi Brilianti Kuhuwael","nip":"197302272022212004","jenis_kelamin":"P","tempat_lahir":"Bandung","tanggal_lahir":"1973-02-27","nik":"1802086702730004","no_kk":null,"niy_nigk":null,"nuptk":"5559751652300032","nuks":null,"status_kepegawaian":"PPPK","jenis_ptk_id":"3 ","jenis_ptk":"Guru Kelas","pengawas_bidang_studi":null,"agama":"Kristen","kewarganegaraan":"ID","alamat_jalan":"RT 1 RW 1 Rama Murti","rt":null,"rw":null,"nama_dusun":null,"desa_kelurahan":"Rama Murti","kode_kecamatan":"120207  ","kecamatan":"Kec. Seputih Raman","kode_kabupaten":"120200  ","kabupaten":"Kab. Lampung Tengah","kode_provinsi":"120000  ","provinsi":"Prov. Lampung","kode_pos":null,"lintang":-4.912304,"bujur":105.37121,"no_telepon_rumah":null,"no_hp":"085379634865","email":"margibrillianti@gmail.com","status_keaktifan":"Aktif","sk_cpns":null,"tgl_cpns":null,"sk_pengangkatan":"810/460/B.a.VII.04/2022","tmt_pengangkatan":"2022-03-01","lembaga_pengangkat":"Pemerintah Kab/Kota","pangkat_golongan":"-","keahlian_laboratorium":"Lainnya","sumber_gaji":"APBD Kabupaten/Kota","nama_ibu_kandung":"Winny Tupenalay","status_perkawinan":"1","nama_suami_istri":"Alfred Ruben Gordon T.","nip_suami_istri":null,"pekerjaan_suami_istri":99,"tmt_pns":"2022-03-01","sudah_lisensi_kepala_sekolah":"0","jumlah_sekolah_binaan":0,"pernah_diklat_kepengawasan":"0","nm_wp":null,"status_data":0,"karpeg":null,"karpas":null,"mampu_handle_kk":"0","keahlian_braille":"0","keahlian_bhs_isyarat":"0","npwp":null,"bank":null,"rekening_bank":null,"rekening_atas_nama":null,"tahun_ajaran":"2022/2023","nomor_surat_tugas":"810/460/B.a.VII.04/2022","tanggal_surat_tugas":"2022-08-12","tmt_tugas":"2022-08-12","ptk_induk":"1","jenis_keluar":null,"tgl_ptk_keluar":null,"riwayat_kepangkatan_pangkat_golongan":null,"riwayat_kepangkatan_nomor_sk":null,"riwayat_kepangkatan_tanggal_sk":null,"riwayat_kepangkatan_tmt_pangkat":null,"riwayat_kepangkatan_masa_kerja_gol_tahun":null,"riwayat_kepangkatan_masa_kerja_gol_bulan":null,"riwayat_gaji_berkala_pangkat_golongan":null,"riwayat_gaji_berkala_nomor_sk":null,"riwayat_gaji_berkala_tanggal_sk":null,"riwayat_gaji_berkala_tmt_kgb":null,"riwayat_gaji_berkala_masa_kerja_tahun":null,"riwayat_gaji_berkala_masa_kerja_bulan":null,"riwayat_gaji_berkala_gaji_pokok":null,"inpassing_pangkat_golongan":null,"inpassing_no_sk_inpassing":null,"inpassing_tgl_sk_inpassing":null,"inpassing_tmt_inpassing":null,"inpassing_angka_kredit":null,"inpassing_masa_kerja_tahun":null,"inpassing_masa_kerja_bulan":null,"riwayat_sertifikasi_bidang_studi":null,"riwayat_sertifikasi_jenis_sertifikasi":null,"riwayat_sertifikasi_tahun_sertifikasi":null,"riwayat_sertifikasi_nomor_sertifikat":null,"riwayat_sertifikasi_nrg":null,"riwayat_sertifikasi_nomor_peserta":null,"riwayat_pendidikan_formal_bidang_studi":"Ekonomi","riwayat_pendidikan_formal_jenjang_pendidikan":"S1","riwayat_pendidikan_formal_gelar_akademik":"Sarjana Ekonomi","riwayat_pendidikan_formal_satuan_pendidikan_formal":"Universitas Padjadjaran","riwayat_pendidikan_formal_fakultas":"","riwayat_pendidikan_formal_kependidikan":"Tidak","riwayat_pendidikan_formal_tahun_masuk":1991,"riwayat_pendidikan_formal_tahun_lulus":1996,"riwayat_pendidikan_formal_nim":"BIB91007","riwayat_pendidikan_formal_status_kuliah":"Tidak","riwayat_pendidikan_formal_semester":0,"riwayat_pendidikan_formal_ipk":0.0,"jumlah_anak":2,"tugas_tambahan_jabatan_ptk":null,"tugas_tambahan_sekolah":null,"tugas_tambahan_jumlah_jam":null,"tugas_tambahan_nomor_sk":null,"tugas_tambahan_tmt_tambahan":null,"tugas_tambahan_tst_tambahan":null,"riwayat_struktural_jabatan_ptk":null,"riwayat_struktural_sk_struktural":null,"riwayat_struktural_tmt_jabatan":null,"riwayat_fungsional_jabatan_fungsional":null,"riwayat_fungsional_sk_jabfung":null,"riwayat_fungsional_tmt_jabatan":null,"create_date":"2018-02-08T12:08:34.813000","last_update":"2022-08-12T14:18:54.353000","soft_delete_ptk_terdaftar":0,"soft_delete_rwy_kepangkatan":null,"soft_delete_riwayat_gaji_berkala":null,"soft_delete_inpassing":null,"soft_delete_rwy_sertifikasi":null,"soft_delete_rwy_pend_formal":0,"soft_delete_tugas_tambahan":null,"soft_delete_rwy_struktural":null,"soft_delete_rwy_fungsional":null},{"ptk_id":"9fc5ba47-67bd-4488-808b-5bbb31ba5f20","semester_id":"20222","sekolah_id":"c09cc86f-8b18-e111-b090-314ae660b182","ptk_terdaftar_id":"2df32a08-554c-4d8f-94dc-90e65d497191","nama":"NYOMAN TRI YULIANTI","nip":"199108282020122009","jenis_kelamin":"P","tempat_lahir":"SEPUTIH RAMAN","tanggal_lahir":"1991-08-28","nik":"1802086808910004","no_kk":null,"niy_nigk":null,"nuptk":"9160769670130103","nuks":null,"status_kepegawaian":"PNS","jenis_ptk_id":"3 ","jenis_ptk":"Guru Kelas","pengawas_bidang_studi":null,"agama":"Hindu","kewarganegaraan":"ID","alamat_jalan":"RAMA DEWA","rt":null,"rw":null,"nama_dusun":null,"desa_kelurahan":"RAMA DEWA","kode_kecamatan":"120207  ","kecamatan":"Kec. Seputih Raman","kode_kabupaten":"120200  ","kabupaten":"Kab. Lampung Tengah","kode_provinsi":"120000  ","provinsi":"Prov. Lampung","kode_pos":"34155","lintang":null,"bujur":null,"no_telepon_rumah":null,"no_hp":null,"email":"nyomantriyulianti@gmail.com","status_keaktifan":"Aktif","sk_cpns":"810/1419/B.a.VII.04/2020","tgl_cpns":"2020-12-01","sk_pengangkatan":"810/1419/B.a.VII.04/2020","tmt_pengangkatan":"2020-12-01","lembaga_pengangkat":"Pemerintah Pusat","pangkat_golongan":null,"keahlian_laboratorium":"Lainnya","sumber_gaji":"APBD Kabupaten/Kota","nama_ibu_kandung":"NI WAYAN PONCOWATI","status_perkawinan":"1","nama_suami_istri":null,"nip_suami_istri":null,"pekerjaan_suami_istri":90,"tmt_pns":"2021-12-01","sudah_lisensi_kepala_sekolah":"0","jumlah_sekolah_binaan":0,"pernah_diklat_kepengawasan":"0","nm_wp":null,"status_data":0,"karpeg":null,"karpas":null,"mampu_handle_kk":"0","keahlian_braille":"0","keahlian_bhs_isyarat":"0","npwp":null,"bank":null,"rekening_bank":null,"rekening_atas_nama":null,"tahun_ajaran":"2022/2023","nomor_surat_tugas":"421.2/66/C.10/D.1/2018","tanggal_surat_tugas":"2017-07-17","tmt_tugas":"2017-07-17","ptk_induk":"1","jenis_keluar":null,"tgl_ptk_keluar":null,"riwayat_kepangkatan_pangkat_golongan":"III/a","riwayat_kepangkatan_nomor_sk":"821.12/856/B.a.VII.04/2021","riwayat_kepangkatan_tanggal_sk":"2021-11-30","riwayat_kepangkatan_tmt_pangkat":"2021-12-01","riwayat_kepangkatan_masa_kerja_gol_tahun":1,"riwayat_kepangkatan_masa_kerja_gol_bulan":0,"riwayat_gaji_berkala_pangkat_golongan":"III/a","riwayat_gaji_berkala_nomor_sk":"810/1419/B.a.VII.04/2020","riwayat_gaji_berkala_tanggal_sk":"2020-12-01","riwayat_gaji_berkala_tmt_kgb":"2020-12-01","riwayat_gaji_berkala_masa_kerja_tahun":0,"riwayat_gaji_berkala_masa_kerja_bulan":1,"riwayat_gaji_berkala_gaji_pokok":2063520,"inpassing_pangkat_golongan":null,"inpassing_no_sk_inpassing":null,"inpassing_tgl_sk_inpassing":null,"inpassing_tmt_inpassing":null,"inpassing_angka_kredit":null,"inpassing_masa_kerja_tahun":null,"inpassing_masa_kerja_bulan":null,"riwayat_sertifikasi_bidang_studi":"Guru Kelas SD/MI","riwayat_sertifikasi_jenis_sertifikasi":"Sertifikasi Pendidik","riwayat_sertifikasi_tahun_sertifikasi":null,"riwayat_sertifikasi_nomor_sertifikat":"0010262202720801","riwayat_sertifikasi_nrg":null,"riwayat_sertifikasi_nomor_peserta":"2213061844","riwayat_pendidikan_formal_bidang_studi":"Guru Kelas SD/MI","riwayat_pendidikan_formal_jenjang_pendidikan":"S1","riwayat_pendidikan_formal_gelar_akademik":"Sarjana Pendidikan","riwayat_pendidikan_formal_satuan_pendidikan_formal":"Universitas Lampung","riwayat_pendidikan_formal_fakultas":"","riwayat_pendidikan_formal_kependidikan":"Ya","riwayat_pendidikan_formal_tahun_masuk":2010,"riwayat_pendidikan_formal_tahun_lulus":2014,"riwayat_pendidikan_formal_nim":"1013053070","riwayat_pendidikan_formal_status_kuliah":"Tidak","riwayat_pendidikan_formal_semester":8,"riwayat_pendidikan_formal_ipk":3.0,"jumlah_anak":null,"tugas_tambahan_jabatan_ptk":null,"tugas_tambahan_sekolah":null,"tugas_tambahan_jumlah_jam":null,"tugas_tambahan_nomor_sk":null,"tugas_tambahan_tmt_tambahan":null,"tugas_tambahan_tst_tambahan":null,"riwayat_struktural_jabatan_ptk":null,"riwayat_struktural_sk_struktural":null,"riwayat_struktural_tmt_jabatan":null,"riwayat_fungsional_jabatan_fungsional":null,"riwayat_fungsional_sk_jabfung":null,"riwayat_fungsional_tmt_jabatan":null,"create_date":"2019-08-30T12:27:58.613000","last_update":"2022-01-28T14:50:06.433000","soft_delete_ptk_terdaftar":0,"soft_delete_rwy_kepangkatan":0,"soft_delete_riwayat_gaji_berkala":0,"soft_delete_inpassing":null,"soft_delete_rwy_sertifikasi":0,"soft_delete_rwy_pend_formal":0,"soft_delete_tugas_tambahan":null,"soft_delete_rwy_struktural":null,"soft_delete_rwy_fungsional":null},{"ptk_id":"5795d338-cb65-45a2-bb16-937dbc240fbe","semester_id":"20222","sekolah_id":"c09cc86f-8b18-e111-b090-314ae660b182","ptk_terdaftar_id":"d6889a2d-8e65-4adc-8fc3-ab14d0f3145b","nama":"NI WAYAN DEVI NOVIA","nip":null,"jenis_kelamin":"P","tempat_lahir":"RAMA INDRA","tanggal_lahir":"1996-11-09","nik":"1802084911960001","no_kk":null,"niy_nigk":null,"nuptk":null,"nuks":null,"status_kepegawaian":"Guru Honor Sekolah","jenis_ptk_id":"3 ","jenis_ptk":"Guru Kelas","pengawas_bidang_studi":null,"agama":"Hindu","kewarganegaraan":"ID","alamat_jalan":"RAMA DEWA","rt":null,"rw":null,"nama_dusun":null,"desa_kelurahan":"RAMA DEWA","kode_kecamatan":"120207  ","kecamatan":"Kec. Seputih Raman","kode_kabupaten":"120200  ","kabupaten":"Kab. Lampung Tengah","kode_provinsi":"120000  ","provinsi":"Prov. Lampung","kode_pos":null,"lintang":null,"bujur":null,"no_telepon_rumah":null,"no_hp":null,"email":"devinovia114@gmail.com","status_keaktifan":"Aktif","sk_cpns":null,"tgl_cpns":null,"sk_pengangkatan":"421.2/22/C.1/D.a.IV.01/2020","tmt_pengangkatan":"2020-07-16","lembaga_pengangkat":"Kepala Sekolah","pangkat_golongan":null,"keahlian_laboratorium":null,"sumber_gaji":"Sekolah","nama_ibu_kandung":"NI NYOMAN SEKARINI","status_perkawinan":"1","nama_suami_istri":null,"nip_suami_istri":null,"pekerjaan_suami_istri":99,"tmt_pns":null,"sudah_lisensi_kepala_sekolah":"0","jumlah_sekolah_binaan":null,"pernah_diklat_kepengawasan":"0","nm_wp":null,"status_data":null,"karpeg":null,"karpas":null,"mampu_handle_kk":"0","keahlian_braille":"0","keahlian_bhs_isyarat":"0","npwp":null,"bank":null,"rekening_bank":null,"rekening_atas_nama":null,"tahun_ajaran":"2022/2023","nomor_surat_tugas":"421.2/22/C.1/D.a.IV.01/2020","tanggal_surat_tugas":"2020-07-16","tmt_tugas":"2020-07-16","ptk_induk":"1","jenis_keluar":null,"tgl_ptk_keluar":null,"riwayat_kepangkatan_pangkat_golongan":null,"riwayat_kepangkatan_nomor_sk":null,"riwayat_kepangkatan_tanggal_sk":null,"riwayat_kepangkatan_tmt_pangkat":null,"riwayat_kepangkatan_masa_kerja_gol_tahun":null,"riwayat_kepangkatan_masa_kerja_gol_bulan":null,"riwayat_gaji_berkala_pangkat_golongan":null,"riwayat_gaji_berkala_nomor_sk":null,"riwayat_gaji_berkala_tanggal_sk":null,"riwayat_gaji_berkala_tmt_kgb":null,"riwayat_gaji_berkala_masa_kerja_tahun":null,"riwayat_gaji_berkala_masa_kerja_bulan":null,"riwayat_gaji_berkala_gaji_pokok":null,"inpassing_pangkat_golongan":null,"inpassing_no_sk_inpassing":null,"inpassing_tgl_sk_inpassing":null,"inpassing_tmt_inpassing":null,"inpassing_angka_kredit":null,"inpassing_masa_kerja_tahun":null,"inpassing_masa_kerja_bulan":null,"riwayat_sertifikasi_bidang_studi":null,"riwayat_sertifikasi_jenis_sertifikasi":null,"riwayat_sertifikasi_tahun_sertifikasi":null,"riwayat_sertifikasi_nomor_sertifikat":null,"riwayat_sertifikasi_nrg":null,"riwayat_sertifikasi_nomor_peserta":null,"riwayat_pendidikan_formal_bidang_studi":null,"riwayat_pendidikan_formal_jenjang_pendidikan":null,"riwayat_pendidikan_formal_gelar_akademik":null,"riwayat_pendidikan_formal_satuan_pendidikan_formal":null,"riwayat_pendidikan_formal_fakultas":null,"riwayat_pendidikan_formal_kependidikan":null,"riwayat_pendidikan_formal_tahun_masuk":null,"riwayat_pendidikan_formal_tahun_lulus":null,"riwayat_pendidikan_formal_nim":null,"riwayat_pendidikan_formal_status_kuliah":null,"riwayat_pendidikan_formal_semester":null,"riwayat_pendidikan_formal_ipk":null,"jumlah_anak":null,"tugas_tambahan_jabatan_ptk":null,"tugas_tambahan_sekolah":null,"tugas_tambahan_jumlah_jam":null,"tugas_tambahan_nomor_sk":null,"tugas_tambahan_tmt_tambahan":null,"tugas_tambahan_tst_tambahan":null,"riwayat_struktural_jabatan_ptk":null,"riwayat_struktural_sk_struktural":null,"riwayat_struktural_tmt_jabatan":null,"riwayat_fungsional_jabatan_fungsional":null,"riwayat_fungsional_sk_jabfung":null,"riwayat_fungsional_tmt_jabatan":null,"create_date":"2022-10-27T09:00:05.257000","last_update":"2022-11-02T13:30:16.220000","soft_delete_ptk_terdaftar":0,"soft_delete_rwy_kepangkatan":null,"soft_delete_riwayat_gaji_berkala":null,"soft_delete_inpassing":null,"soft_delete_rwy_sertifikasi":null,"soft_delete_rwy_pend_formal":null,"soft_delete_tugas_tambahan":null,"soft_delete_rwy_struktural":null,"soft_delete_rwy_fungsional":null},{"ptk_id":"814f84d0-eea8-4ed8-b109-b832901cf52d","semester_id":"20222","sekolah_id":"c09cc86f-8b18-e111-b090-314ae660b182","ptk_terdaftar_id":"e6974399-efca-4e64-816f-49704f1d08a1","nama":"Made Dwi Andriyani","nip":"199306162022212020","jenis_kelamin":"P","tempat_lahir":"RAMA GUNAWAN","tanggal_lahir":"1993-06-16","nik":"1802085606930002","no_kk":null,"niy_nigk":null,"nuptk":"1948771672230112","nuks":null,"status_kepegawaian":"PPPK","jenis_ptk_id":"3 ","jenis_ptk":"Guru Kelas","pengawas_bidang_studi":null,"agama":"Hindu","kewarganegaraan":"ID","alamat_jalan":"DUSUN 2","rt":null,"rw":null,"nama_dusun":null,"desa_kelurahan":"RAMA GUNAWAN","kode_kecamatan":"120207  ","kecamatan":"Kec. Seputih Raman","kode_kabupaten":"120200  ","kabupaten":"Kab. Lampung Tengah","kode_provinsi":"120000  ","provinsi":"Prov. Lampung","kode_pos":null,"lintang":null,"bujur":null,"no_telepon_rumah":null,"no_hp":"082183977926","email":"dwiandriyanimade@gmail.com","status_keaktifan":"Aktif","sk_cpns":null,"tgl_cpns":null,"sk_pengangkatan":"810/460/B.a.VII.04/2022","tmt_pengangkatan":"2022-03-01","lembaga_pengangkat":"Pemerintah Kab/Kota","pangkat_golongan":"-","keahlian_laboratorium":"Lainnya","sumber_gaji":"APBD Kabupaten/Kota","nama_ibu_kandung":"NI WAYAN SUKEJATI","status_perkawinan":"1","nama_suami_istri":"WAYAN ADITYA ARISKA","nip_suami_istri":null,"pekerjaan_suami_istri":90,"tmt_pns":"2022-03-01","sudah_lisensi_kepala_sekolah":"1","jumlah_sekolah_binaan":0,"pernah_diklat_kepengawasan":"0","nm_wp":null,"status_data":0,"karpeg":null,"karpas":null,"mampu_handle_kk":"0","keahlian_braille":"0","keahlian_bhs_isyarat":"0","npwp":null,"bank":null,"rekening_bank":null,"rekening_atas_nama":null,"tahun_ajaran":"2022/2023","nomor_surat_tugas":"810/460/B.a.VII.04/2022","tanggal_surat_tugas":"2022-08-12","tmt_tugas":"2022-08-12","ptk_induk":"1","jenis_keluar":null,"tgl_ptk_keluar":null,"riwayat_kepangkatan_pangkat_golongan":null,"riwayat_kepangkatan_nomor_sk":null,"riwayat_kepangkatan_tanggal_sk":null,"riwayat_kepangkatan_tmt_pangkat":null,"riwayat_kepangkatan_masa_kerja_gol_tahun":null,"riwayat_kepangkatan_masa_kerja_gol_bulan":null,"riwayat_gaji_berkala_pangkat_golongan":null,"riwayat_gaji_berkala_nomor_sk":null,"riwayat_gaji_berkala_tanggal_sk":null,"riwayat_gaji_berkala_tmt_kgb":null,"riwayat_gaji_berkala_masa_kerja_tahun":null,"riwayat_gaji_berkala_masa_kerja_bulan":null,"riwayat_gaji_berkala_gaji_pokok":null,"inpassing_pangkat_golongan":null,"inpassing_no_sk_inpassing":null,"inpassing_tgl_sk_inpassing":null,"inpassing_tmt_inpassing":null,"inpassing_angka_kredit":null,"inpassing_masa_kerja_tahun":null,"inpassing_masa_kerja_bulan":null,"riwayat_sertifikasi_bidang_studi":null,"riwayat_sertifikasi_jenis_sertifikasi":null,"riwayat_sertifikasi_tahun_sertifikasi":null,"riwayat_sertifikasi_nomor_sertifikat":null,"riwayat_sertifikasi_nrg":null,"riwayat_sertifikasi_nomor_peserta":null,"riwayat_pendidikan_formal_bidang_studi":"Guru Kelas SD/MI","riwayat_pendidikan_formal_jenjang_pendidikan":"S1","riwayat_pendidikan_formal_gelar_akademik":"Sarjana Pendidikan","riwayat_pendidikan_formal_satuan_pendidikan_formal":"","riwayat_pendidikan_formal_fakultas":"","riwayat_pendidikan_formal_kependidikan":"Ya","riwayat_pendidikan_formal_tahun_masuk":2011,"riwayat_pendidikan_formal_tahun_lulus":2017,"riwayat_pendidikan_formal_nim":"121350046","riwayat_pendidikan_formal_status_kuliah":"Tidak","riwayat_pendidikan_formal_semester":0,"riwayat_pendidikan_formal_ipk":0.0,"jumlah_anak":null,"tugas_tambahan_jabatan_ptk":null,"tugas_tambahan_sekolah":null,"tugas_tambahan_jumlah_jam":null,"tugas_tambahan_nomor_sk":null,"tugas_tambahan_tmt_tambahan":null,"tugas_tambahan_tst_tambahan":null,"riwayat_struktural_jabatan_ptk":null,"riwayat_struktural_sk_struktural":null,"riwayat_struktural_tmt_jabatan":null,"riwayat_fungsional_jabatan_fungsional":null,"riwayat_fungsional_sk_jabfung":null,"riwayat_fungsional_tmt_jabatan":null,"create_date":"2018-01-24T11:23:02.553000","last_update":"2022-08-12T14:28:30.770000","soft_delete_ptk_terdaftar":0,"soft_delete_rwy_kepangkatan":null,"soft_delete_riwayat_gaji_berkala":null,"soft_delete_inpassing":null,"soft_delete_rwy_sertifikasi":null,"soft_delete_rwy_pend_formal":0,"soft_delete_tugas_tambahan":null,"soft_delete_rwy_struktural":null,"soft_delete_rwy_fungsional":null},{"ptk_id":"b12721a3-aa07-e211-a8e1-df0543f6e3e9","semester_id":"20222","sekolah_id":"c09cc86f-8b18-e111-b090-314ae660b182","ptk_terdaftar_id":"95cbc0e8-5c9f-47ed-9466-a587f04716f7","nama":"Rasminah","nip":"196910151993082001","jenis_kelamin":"P","tempat_lahir":"CANDIMAS","tanggal_lahir":"1969-10-15","nik":"1802085510690002","no_kk":null,"niy_nigk":null,"nuptk":"2347747650300013","nuks":null,"status_kepegawaian":"PNS","jenis_ptk_id":"3 ","jenis_ptk":"Guru Kelas","pengawas_bidang_studi":"lainnya","agama":"Hindu","kewarganegaraan":"ID","alamat_jalan":"RAMA GUNAWAN","rt":1,"rw":1,"nama_dusun":null,"desa_kelurahan":"RAMA GUNAWAN","kode_kecamatan":"120207  ","kecamatan":"Kec. Seputih Raman","kode_kabupaten":"120200  ","kabupaten":"Kab. Lampung Tengah","kode_provinsi":"120000  ","provinsi":"Prov. Lampung","kode_pos":"34155","lintang":null,"bujur":null,"no_telepon_rumah":null,"no_hp":null,"email":"rasminah16@gmail.com","status_keaktifan":"Aktif","sk_cpns":"813.5/497/13/1993","tgl_cpns":"1993-08-01","sk_pengangkatan":"813.5/497/13/1993","tmt_pengangkatan":"1993-08-01","lembaga_pengangkat":"Pemerintah Pusat","pangkat_golongan":"IV/a","keahlian_laboratorium":"Lainnya","sumber_gaji":"APBD Kabupaten/Kota","nama_ibu_kandung":"TITI MAI TUMPI","status_perkawinan":"1","nama_suami_istri":"I KETUT ARYATAMA","nip_suami_istri":"1965081019880810  ","pekerjaan_suami_istri":5,"tmt_pns":"1994-10-01","sudah_lisensi_kepala_sekolah":"0","jumlah_sekolah_binaan":0,"pernah_diklat_kepengawasan":"0","nm_wp":null,"status_data":0,"karpeg":null,"karpas":null,"mampu_handle_kk":"0","keahlian_braille":"0","keahlian_bhs_isyarat":"0","npwp":null,"bank":null,"rekening_bank":null,"rekening_atas_nama":null,"tahun_ajaran":"2022/2023","nomor_surat_tugas":"821.29/937/01/2010","tanggal_surat_tugas":"2010-05-27","tmt_tugas":"2010-05-27","ptk_induk":"1","jenis_keluar":null,"tgl_ptk_keluar":null,"riwayat_kepangkatan_pangkat_golongan":"IV/b","riwayat_kepangkatan_nomor_sk":"823.4/227.1/VI.04/2020","riwayat_kepangkatan_tanggal_sk":"2020-06-29","riwayat_kepangkatan_tmt_pangkat":"2020-04-01","riwayat_kepangkatan_masa_kerja_gol_tahun":21,"riwayat_kepangkatan_masa_kerja_gol_bulan":8,"riwayat_gaji_berkala_pangkat_golongan":"IV/b","riwayat_gaji_berkala_nomor_sk":"823.4/1879/B.a.VII.04/2022","riwayat_gaji_berkala_tanggal_sk":"2022-06-27","riwayat_gaji_berkala_tmt_kgb":"2022-08-01","riwayat_gaji_berkala_masa_kerja_tahun":24,"riwayat_gaji_berkala_masa_kerja_bulan":0,"riwayat_gaji_berkala_gaji_pokok":4603500,"inpassing_pangkat_golongan":"II/d","inpassing_no_sk_inpassing":"800/355/LTD.5/2003","inpassing_tgl_sk_inpassing":null,"inpassing_tmt_inpassing":"2013-01-01","inpassing_angka_kredit":0,"inpassing_masa_kerja_tahun":9,"inpassing_masa_kerja_bulan":5,"riwayat_sertifikasi_bidang_studi":"Guru Kelas SD/MI","riwayat_sertifikasi_jenis_sertifikasi":"Sertifikasi Pendidik","riwayat_sertifikasi_tahun_sertifikasi":null,"riwayat_sertifikasi_nomor_sertifikat":"1071302702604","riwayat_sertifikasi_nrg":null,"riwayat_sertifikasi_nomor_peserta":"13120202710321","riwayat_pendidikan_formal_bidang_studi":null,"riwayat_pendidikan_formal_jenjang_pendidikan":null,"riwayat_pendidikan_formal_gelar_akademik":null,"riwayat_pendidikan_formal_satuan_pendidikan_formal":null,"riwayat_pendidikan_formal_fakultas":null,"riwayat_pendidikan_formal_kependidikan":null,"riwayat_pendidikan_formal_tahun_masuk":null,"riwayat_pendidikan_formal_tahun_lulus":null,"riwayat_pendidikan_formal_nim":null,"riwayat_pendidikan_formal_status_kuliah":null,"riwayat_pendidikan_formal_semester":null,"riwayat_pendidikan_formal_ipk":null,"jumlah_anak":4,"tugas_tambahan_jabatan_ptk":null,"tugas_tambahan_sekolah":null,"tugas_tambahan_jumlah_jam":null,"tugas_tambahan_nomor_sk":null,"tugas_tambahan_tmt_tambahan":null,"tugas_tambahan_tst_tambahan":null,"riwayat_struktural_jabatan_ptk":"Guru","riwayat_struktural_sk_struktural":"****","riwayat_struktural_tmt_jabatan":"2010-10-01","riwayat_fungsional_jabatan_fungsional":null,"riwayat_fungsional_sk_jabfung":null,"riwayat_fungsional_tmt_jabatan":null,"create_date":"2018-01-24T11:23:02.553000","last_update":"2020-11-02T17:46:33.120000","soft_delete_ptk_terdaftar":0,"soft_delete_rwy_kepangkatan":0,"soft_delete_riwayat_gaji_berkala":0,"soft_delete_inpassing":0,"soft_delete_rwy_sertifikasi":0,"soft_delete_rwy_pend_formal":null,"soft_delete_tugas_tambahan":null,"soft_delete_rwy_struktural":0,"soft_delete_rwy_fungsional":null},{"ptk_id":"bd330b3b-ae07-e211-a8e6-df0543f6e3e9","semester_id":"20222","sekolah_id":"c09cc86f-8b18-e111-b090-314ae660b182","ptk_terdaftar_id":"2456fdf8-b01d-441c-a405-be18673a8f0c","nama":"Istikomah","nip":"198602022022212027","jenis_kelamin":"P","tempat_lahir":"PEMALANG","tanggal_lahir":"1986-02-02","nik":"1802084202860005","no_kk":null,"niy_nigk":null,"nuptk":"1534764666200022","nuks":null,"status_kepegawaian":"PPPK","jenis_ptk_id":"3 ","jenis_ptk":"Guru Kelas","pengawas_bidang_studi":"lainnya","agama":"Islam","kewarganegaraan":"ID","alamat_jalan":"rukti harjo","rt":4,"rw":6,"nama_dusun":null,"desa_kelurahan":"RUKTI HARJO","kode_kecamatan":"120207  ","kecamatan":"Kec. Seputih Raman","kode_kabupaten":"120200  ","kabupaten":"Kab. Lampung Tengah","kode_provinsi":"120000  ","provinsi":"Prov. Lampung","kode_pos":"34155","lintang":null,"bujur":null,"no_telepon_rumah":null,"no_hp":"082376204422","email":"istikomah816@gmail.com","status_keaktifan":"Aktif","sk_cpns":null,"tgl_cpns":null,"sk_pengangkatan":"810/431/B.a.VII.04/2022","tmt_pengangkatan":"2022-02-01","lembaga_pengangkat":"Pemerintah Kab/Kota","pangkat_golongan":"-","keahlian_laboratorium":"Lainnya","sumber_gaji":"APBD Kabupaten/Kota","nama_ibu_kandung":"INDOFAH","status_perkawinan":"1","nama_suami_istri":"ISWANTORO","nip_suami_istri":null,"pekerjaan_suami_istri":99,"tmt_pns":"2022-02-01","sudah_lisensi_kepala_sekolah":"0","jumlah_sekolah_binaan":0,"pernah_diklat_kepengawasan":"0","nm_wp":null,"status_data":0,"karpeg":null,"karpas":null,"mampu_handle_kk":"0","keahlian_braille":"0","keahlian_bhs_isyarat":"0","npwp":null,"bank":null,"rekening_bank":null,"rekening_atas_nama":null,"tahun_ajaran":"2022/2023","nomor_surat_tugas":"420/18/02/C.7/2006","tanggal_surat_tugas":"2006-07-08","tmt_tugas":"2006-07-09","ptk_induk":"1","jenis_keluar":null,"tgl_ptk_keluar":null,"riwayat_kepangkatan_pangkat_golongan":null,"riwayat_kepangkatan_nomor_sk":null,"riwayat_kepangkatan_tanggal_sk":null,"riwayat_kepangkatan_tmt_pangkat":null,"riwayat_kepangkatan_masa_kerja_gol_tahun":null,"riwayat_kepangkatan_masa_kerja_gol_bulan":null,"riwayat_gaji_berkala_pangkat_golongan":null,"riwayat_gaji_berkala_nomor_sk":null,"riwayat_gaji_berkala_tanggal_sk":null,"riwayat_gaji_berkala_tmt_kgb":null,"riwayat_gaji_berkala_masa_kerja_tahun":null,"riwayat_gaji_berkala_masa_kerja_bulan":null,"riwayat_gaji_berkala_gaji_pokok":null,"inpassing_pangkat_golongan":null,"inpassing_no_sk_inpassing":null,"inpassing_tgl_sk_inpassing":null,"inpassing_tmt_inpassing":null,"inpassing_angka_kredit":null,"inpassing_masa_kerja_tahun":null,"inpassing_masa_kerja_bulan":null,"riwayat_sertifikasi_bidang_studi":null,"riwayat_sertifikasi_jenis_sertifikasi":null,"riwayat_sertifikasi_tahun_sertifikasi":null,"riwayat_sertifikasi_nomor_sertifikat":null,"riwayat_sertifikasi_nrg":null,"riwayat_sertifikasi_nomor_peserta":null,"riwayat_pendidikan_formal_bidang_studi":"Guru Kelas SD/MI","riwayat_pendidikan_formal_jenjang_pendidikan":"S1","riwayat_pendidikan_formal_gelar_akademik":"Sarjana Pendidikan","riwayat_pendidikan_formal_satuan_pendidikan_formal":"","riwayat_pendidikan_formal_fakultas":"","riwayat_pendidikan_formal_kependidikan":"Ya","riwayat_pendidikan_formal_tahun_masuk":2011,"riwayat_pendidikan_formal_tahun_lulus":2016,"riwayat_pendidikan_formal_nim":"823201019","riwayat_pendidikan_formal_status_kuliah":"Tidak","riwayat_pendidikan_formal_semester":10,"riwayat_pendidikan_formal_ipk":3.0,"jumlah_anak":null,"tugas_tambahan_jabatan_ptk":null,"tugas_tambahan_sekolah":null,"tugas_tambahan_jumlah_jam":null,"tugas_tambahan_nomor_sk":null,"tugas_tambahan_tmt_tambahan":null,"tugas_tambahan_tst_tambahan":null,"riwayat_struktural_jabatan_ptk":null,"riwayat_struktural_sk_struktural":null,"riwayat_struktural_tmt_jabatan":null,"riwayat_fungsional_jabatan_fungsional":null,"riwayat_fungsional_sk_jabfung":null,"riwayat_fungsional_tmt_jabatan":null,"create_date":"2018-01-24T11:23:02.553000","last_update":"2022-08-10T19:41:20.967000","soft_delete_ptk_terdaftar":0,"soft_delete_rwy_kepangkatan":null,"soft_delete_riwayat_gaji_berkala":null,"soft_delete_inpassing":null,"soft_delete_rwy_sertifikasi":null,"soft_delete_rwy_pend_formal":0,"soft_delete_tugas_tambahan":null,"soft_delete_rwy_struktural":null,"soft_delete_rwy_fungsional":null},{"ptk_id":"c104664a-ae07-e211-a8e7-df0543f6e3e9","semester_id":"20222","sekolah_id":"c09cc86f-8b18-e111-b090-314ae660b182","ptk_terdaftar_id":"8b920b59-d3ae-4b42-9fe3-4f7f3bd43d0b","nama":"Ni Wayan Sumariyani","nip":null,"jenis_kelamin":"P","tempat_lahir":"rama dewa","tanggal_lahir":"1987-06-03","nik":"1802084306870003","no_kk":null,"niy_nigk":null,"nuptk":"4935765666300092","nuks":null,"status_kepegawaian":"Guru Honor Sekolah","jenis_ptk_id":"3 ","jenis_ptk":"Guru Kelas","pengawas_bidang_studi":"lainnya","agama":"Hindu","kewarganegaraan":"ID","alamat_jalan":"tari bali","rt":3,"rw":2,"nama_dusun":null,"desa_kelurahan":"RAMA DEWA","kode_kecamatan":"120207  ","kecamatan":"Kec. Seputih Raman","kode_kabupaten":"120200  ","kabupaten":"Kab. Lampung Tengah","kode_provinsi":"120000  ","provinsi":"Prov. Lampung","kode_pos":"34155","lintang":null,"bujur":null,"no_telepon_rumah":null,"no_hp":"085269597966","email":"niwayansumariyani@gmail.com","status_keaktifan":"Aktif","sk_cpns":null,"tgl_cpns":null,"sk_pengangkatan":"422/12/02/D.1/2006","tmt_pengangkatan":"2006-10-10","lembaga_pengangkat":"Kepala Sekolah","pangkat_golongan":"-","keahlian_laboratorium":"Lainnya","sumber_gaji":"Sekolah","nama_ibu_kandung":"NI MADE KARTI","status_perkawinan":"1","nama_suami_istri":null,"nip_suami_istri":null,"pekerjaan_suami_istri":99,"tmt_pns":null,"sudah_lisensi_kepala_sekolah":"0","jumlah_sekolah_binaan":0,"pernah_diklat_kepengawasan":"0","nm_wp":null,"status_data":0,"karpeg":null,"karpas":null,"mampu_handle_kk":"0","keahlian_braille":"0","keahlian_bhs_isyarat":"0","npwp":null,"bank":null,"rekening_bank":null,"rekening_atas_nama":null,"tahun_ajaran":"2022/2023","nomor_surat_tugas":"422/12/02/D.1/2006","tanggal_surat_tugas":"2006-10-10","tmt_tugas":"2006-10-01","ptk_induk":"1","jenis_keluar":null,"tgl_ptk_keluar":null,"riwayat_kepangkatan_pangkat_golongan":null,"riwayat_kepangkatan_nomor_sk":null,"riwayat_kepangkatan_tanggal_sk":null,"riwayat_kepangkatan_tmt_pangkat":null,"riwayat_kepangkatan_masa_kerja_gol_tahun":null,"riwayat_kepangkatan_masa_kerja_gol_bulan":null,"riwayat_gaji_berkala_pangkat_golongan":null,"riwayat_gaji_berkala_nomor_sk":null,"riwayat_gaji_berkala_tanggal_sk":null,"riwayat_gaji_berkala_tmt_kgb":null,"riwayat_gaji_berkala_masa_kerja_tahun":null,"riwayat_gaji_berkala_masa_kerja_bulan":null,"riwayat_gaji_berkala_gaji_pokok":null,"inpassing_pangkat_golongan":null,"inpassing_no_sk_inpassing":null,"inpassing_tgl_sk_inpassing":null,"inpassing_tmt_inpassing":null,"inpassing_angka_kredit":null,"inpassing_masa_kerja_tahun":null,"inpassing_masa_kerja_bulan":null,"riwayat_sertifikasi_bidang_studi":null,"riwayat_sertifikasi_jenis_sertifikasi":null,"riwayat_sertifikasi_tahun_sertifikasi":null,"riwayat_sertifikasi_nomor_sertifikat":null,"riwayat_sertifikasi_nrg":null,"riwayat_sertifikasi_nomor_peserta":null,"riwayat_pendidikan_formal_bidang_studi":"Guru Kelas SD/MI","riwayat_pendidikan_formal_jenjang_pendidikan":"S1","riwayat_pendidikan_formal_gelar_akademik":"Sarjana Pendidikan","riwayat_pendidikan_formal_satuan_pendidikan_formal":"","riwayat_pendidikan_formal_fakultas":"","riwayat_pendidikan_formal_kependidikan":"Ya","riwayat_pendidikan_formal_tahun_masuk":2009,"riwayat_pendidikan_formal_tahun_lulus":2014,"riwayat_pendidikan_formal_nim":"818636287","riwayat_pendidikan_formal_status_kuliah":"Tidak","riwayat_pendidikan_formal_semester":0,"riwayat_pendidikan_formal_ipk":3.12,"jumlah_anak":null,"tugas_tambahan_jabatan_ptk":null,"tugas_tambahan_sekolah":null,"tugas_tambahan_jumlah_jam":null,"tugas_tambahan_nomor_sk":null,"tugas_tambahan_tmt_tambahan":null,"tugas_tambahan_tst_tambahan":null,"riwayat_struktural_jabatan_ptk":null,"riwayat_struktural_sk_struktural":null,"riwayat_struktural_tmt_jabatan":null,"riwayat_fungsional_jabatan_fungsional":null,"riwayat_fungsional_sk_jabfung":null,"riwayat_fungsional_tmt_jabatan":null,"create_date":"2018-01-24T11:23:02.553000","last_update":"2020-11-02T17:46:33.120000","soft_delete_ptk_terdaftar":0,"soft_delete_rwy_kepangkatan":null,"soft_delete_riwayat_gaji_berkala":null,"soft_delete_inpassing":null,"soft_delete_rwy_sertifikasi":null,"soft_delete_rwy_pend_formal":0,"soft_delete_tugas_tambahan":null,"soft_delete_rwy_struktural":null,"soft_delete_rwy_fungsional":null},{"ptk_id":"440983a8-ae07-e211-a8e8-df0543f6e3e9","semester_id":"20222","sekolah_id":"c09cc86f-8b18-e111-b090-314ae660b182","ptk_terdaftar_id":"77986d1a-ebed-4e9d-8e78-bfbe539c5fcc","nama":"Ni Made Diah Komala","nip":"198203052022212026","jenis_kelamin":"P","tempat_lahir":"RAMA DEWA","tanggal_lahir":"1982-03-05","nik":"1802084503820005","no_kk":null,"niy_nigk":null,"nuptk":"6637760660130182","nuks":null,"status_kepegawaian":"PPPK","jenis_ptk_id":"3 ","jenis_ptk":"Guru Kelas","pengawas_bidang_studi":"lainnya","agama":"Hindu","kewarganegaraan":"ID","alamat_jalan":"Jl. Pentas Tari Bali","rt":2,"rw":4,"nama_dusun":null,"desa_kelurahan":"RAMA DEWA","kode_kecamatan":"120207  ","kecamatan":"Kec. Seputih Raman","kode_kabupaten":"120200  ","kabupaten":"Kab. Lampung Tengah","kode_provinsi":"120000  ","provinsi":"Prov. Lampung","kode_pos":"34155","lintang":null,"bujur":null,"no_telepon_rumah":null,"no_hp":null,"email":"nimadediahkomala@gmail.com","status_keaktifan":"Aktif","sk_cpns":null,"tgl_cpns":null,"sk_pengangkatan":"810/460/B.a.VII.04/2022","tmt_pengangkatan":"2022-03-01","lembaga_pengangkat":"Pemerintah Kab/Kota","pangkat_golongan":"-","keahlian_laboratorium":"Lainnya","sumber_gaji":"APBD Kabupaten/Kota","nama_ibu_kandung":"NI NYOMAN KERTI","status_perkawinan":"1","nama_suami_istri":"I MADE SOPHAN PRIANA","nip_suami_istri":null,"pekerjaan_suami_istri":99,"tmt_pns":"2022-03-01","sudah_lisensi_kepala_sekolah":"0","jumlah_sekolah_binaan":0,"pernah_diklat_kepengawasan":"0","nm_wp":null,"status_data":0,"karpeg":null,"karpas":null,"mampu_handle_kk":"0","keahlian_braille":"0","keahlian_bhs_isyarat":"0","npwp":null,"bank":null,"rekening_bank":null,"rekening_atas_nama":null,"tahun_ajaran":"2022/2023","nomor_surat_tugas":"800/39/C.7/D.1/2008","tanggal_surat_tugas":"2008-07-20","tmt_tugas":"2008-07-21","ptk_induk":"1","jenis_keluar":null,"tgl_ptk_keluar":null,"riwayat_kepangkatan_pangkat_golongan":null,"riwayat_kepangkatan_nomor_sk":null,"riwayat_kepangkatan_tanggal_sk":null,"riwayat_kepangkatan_tmt_pangkat":null,"riwayat_kepangkatan_masa_kerja_gol_tahun":null,"riwayat_kepangkatan_masa_kerja_gol_bulan":null,"riwayat_gaji_berkala_pangkat_golongan":null,"riwayat_gaji_berkala_nomor_sk":null,"riwayat_gaji_berkala_tanggal_sk":null,"riwayat_gaji_berkala_tmt_kgb":null,"riwayat_gaji_berkala_masa_kerja_tahun":null,"riwayat_gaji_berkala_masa_kerja_bulan":null,"riwayat_gaji_berkala_gaji_pokok":null,"inpassing_pangkat_golongan":null,"inpassing_no_sk_inpassing":null,"inpassing_tgl_sk_inpassing":null,"inpassing_tmt_inpassing":null,"inpassing_angka_kredit":null,"inpassing_masa_kerja_tahun":null,"inpassing_masa_kerja_bulan":null,"riwayat_sertifikasi_bidang_studi":null,"riwayat_sertifikasi_jenis_sertifikasi":null,"riwayat_sertifikasi_tahun_sertifikasi":null,"riwayat_sertifikasi_nomor_sertifikat":null,"riwayat_sertifikasi_nrg":null,"riwayat_sertifikasi_nomor_peserta":null,"riwayat_pendidikan_formal_bidang_studi":"Guru Kelas SD/MI","riwayat_pendidikan_formal_jenjang_pendidikan":"S1","riwayat_pendidikan_formal_gelar_akademik":"Sarjana Pendidikan","riwayat_pendidikan_formal_satuan_pendidikan_formal":"","riwayat_pendidikan_formal_fakultas":"","riwayat_pendidikan_formal_kependidikan":"Ya","riwayat_pendidikan_formal_tahun_masuk":2010,"riwayat_pendidikan_formal_tahun_lulus":2015,"riwayat_pendidikan_formal_nim":"820795281","riwayat_pendidikan_formal_status_kuliah":"Tidak","riwayat_pendidikan_formal_semester":0,"riwayat_pendidikan_formal_ipk":3.0,"jumlah_anak":null,"tugas_tambahan_jabatan_ptk":null,"tugas_tambahan_sekolah":null,"tugas_tambahan_jumlah_jam":null,"tugas_tambahan_nomor_sk":null,"tugas_tambahan_tmt_tambahan":null,"tugas_tambahan_tst_tambahan":null,"riwayat_struktural_jabatan_ptk":null,"riwayat_struktural_sk_struktural":null,"riwayat_struktural_tmt_jabatan":null,"riwayat_fungsional_jabatan_fungsional":null,"riwayat_fungsional_sk_jabfung":null,"riwayat_fungsional_tmt_jabatan":null,"create_date":"2018-01-24T11:23:02.553000","last_update":"2022-11-02T13:30:16.220000","soft_delete_ptk_terdaftar":0,"soft_delete_rwy_kepangkatan":null,"soft_delete_riwayat_gaji_berkala":null,"soft_delete_inpassing":null,"soft_delete_rwy_sertifikasi":null,"soft_delete_rwy_pend_formal":0,"soft_delete_tugas_tambahan":null,"soft_delete_rwy_struktural":null,"soft_delete_rwy_fungsional":null},{"ptk_id":"770ed748-eaad-11e3-b0e1-efcb2861e4e7","semester_id":"20222","sekolah_id":"c09cc86f-8b18-e111-b090-314ae660b182","ptk_terdaftar_id":"276935d8-e184-4354-82c1-44f3372b98b5","nama":"I Made Sugiada","nip":null,"jenis_kelamin":"L","tempat_lahir":"RAMA NIRWANA","tanggal_lahir":"1984-06-21","nik":"1802086106860002","no_kk":null,"niy_nigk":"","nuptk":"4953762663130132","nuks":null,"status_kepegawaian":"Guru Honor Sekolah","jenis_ptk_id":"3 ","jenis_ptk":"Guru Kelas","pengawas_bidang_studi":null,"agama":"Hindu","kewarganegaraan":"ID","alamat_jalan":"DUSUN III","rt":13,"rw":3,"nama_dusun":"DUSUN III","desa_kelurahan":"RAMA NIRWANA","kode_kecamatan":"120207  ","kecamatan":"Kec. Seputih Raman","kode_kabupaten":"120200  ","kabupaten":"Kab. Lampung Tengah","kode_provinsi":"120000  ","provinsi":"Prov. Lampung","kode_pos":"34155","lintang":null,"bujur":null,"no_telepon_rumah":"","no_hp":"085316191384","email":"made.sugiada@yahoo.co.id","status_keaktifan":"Aktif","sk_cpns":null,"tgl_cpns":null,"sk_pengangkatan":"421.2/67/C.10/D.1/2016","tmt_pengangkatan":"2016-07-14","lembaga_pengangkat":"Kepala Sekolah","pangkat_golongan":"-","keahlian_laboratorium":null,"sumber_gaji":"Lainnya","nama_ibu_kandung":"NI WAYAN BRATI","status_perkawinan":"1","nama_suami_istri":"NI LUH GEDE WAHYU SETIYANI","nip_suami_istri":null,"pekerjaan_suami_istri":99,"tmt_pns":null,"sudah_lisensi_kepala_sekolah":"0","jumlah_sekolah_binaan":0,"pernah_diklat_kepengawasan":"0","nm_wp":"","status_data":0,"karpeg":"","karpas":"","mampu_handle_kk":"0","keahlian_braille":"0","keahlian_bhs_isyarat":"0","npwp":null,"bank":null,"rekening_bank":"","rekening_atas_nama":"","tahun_ajaran":"2022/2023","nomor_surat_tugas":"421.2/67/C.10/D.1/2012","tanggal_surat_tugas":"2012-07-14","tmt_tugas":"2012-07-14","ptk_induk":"1","jenis_keluar":null,"tgl_ptk_keluar":null,"riwayat_kepangkatan_pangkat_golongan":null,"riwayat_kepangkatan_nomor_sk":null,"riwayat_kepangkatan_tanggal_sk":null,"riwayat_kepangkatan_tmt_pangkat":null,"riwayat_kepangkatan_masa_kerja_gol_tahun":null,"riwayat_kepangkatan_masa_kerja_gol_bulan":null,"riwayat_gaji_berkala_pangkat_golongan":null,"riwayat_gaji_berkala_nomor_sk":null,"riwayat_gaji_berkala_tanggal_sk":null,"riwayat_gaji_berkala_tmt_kgb":null,"riwayat_gaji_berkala_masa_kerja_tahun":null,"riwayat_gaji_berkala_masa_kerja_bulan":null,"riwayat_gaji_berkala_gaji_pokok":null,"inpassing_pangkat_golongan":null,"inpassing_no_sk_inpassing":null,"inpassing_tgl_sk_inpassing":null,"inpassing_tmt_inpassing":null,"inpassing_angka_kredit":null,"inpassing_masa_kerja_tahun":null,"inpassing_masa_kerja_bulan":null,"riwayat_sertifikasi_bidang_studi":null,"riwayat_sertifikasi_jenis_sertifikasi":null,"riwayat_sertifikasi_tahun_sertifikasi":null,"riwayat_sertifikasi_nomor_sertifikat":null,"riwayat_sertifikasi_nrg":null,"riwayat_sertifikasi_nomor_peserta":null,"riwayat_pendidikan_formal_bidang_studi":"Biologi","riwayat_pendidikan_formal_jenjang_pendidikan":"S1","riwayat_pendidikan_formal_gelar_akademik":"Sarjana Pendidikan","riwayat_pendidikan_formal_satuan_pendidikan_formal":"","riwayat_pendidikan_formal_fakultas":"","riwayat_pendidikan_formal_kependidikan":"Ya","riwayat_pendidikan_formal_tahun_masuk":2003,"riwayat_pendidikan_formal_tahun_lulus":2007,"riwayat_pendidikan_formal_nim":"035040116","riwayat_pendidikan_formal_status_kuliah":"Tidak","riwayat_pendidikan_formal_semester":0,"riwayat_pendidikan_formal_ipk":3.1,"jumlah_anak":null,"tugas_tambahan_jabatan_ptk":null,"tugas_tambahan_sekolah":null,"tugas_tambahan_jumlah_jam":null,"tugas_tambahan_nomor_sk":null,"tugas_tambahan_tmt_tambahan":null,"tugas_tambahan_tst_tambahan":null,"riwayat_struktural_jabatan_ptk":null,"riwayat_struktural_sk_struktural":null,"riwayat_struktural_tmt_jabatan":null,"riwayat_fungsional_jabatan_fungsional":null,"riwayat_fungsional_sk_jabfung":null,"riwayat_fungsional_tmt_jabatan":null,"create_date":"2018-01-24T09:35:47.087000","last_update":"2022-02-02T12:05:25.770000","soft_delete_ptk_terdaftar":0,"soft_delete_rwy_kepangkatan":null,"soft_delete_riwayat_gaji_berkala":null,"soft_delete_inpassing":null,"soft_delete_rwy_sertifikasi":null,"soft_delete_rwy_pend_formal":0,"soft_delete_tugas_tambahan":null,"soft_delete_rwy_struktural":null,"soft_delete_rwy_fungsional":null},{"ptk_id":"98929717-ef65-4988-88a5-690e8e02c062","semester_id":"20222","sekolah_id":"c09cc86f-8b18-e111-b090-314ae660b182","ptk_terdaftar_id":"8009aee3-22a5-4a43-a4ab-94c9b19a2238","nama":"I GEDE DWARA  ASTARINA","nip":null,"jenis_kelamin":"L","tempat_lahir":"RAMA GUNAWAN","tanggal_lahir":"1995-04-02","nik":"1802080205940005","no_kk":null,"niy_nigk":null,"nuptk":null,"nuks":null,"status_kepegawaian":"Guru Honor Sekolah","jenis_ptk_id":"4 ","jenis_ptk":"Guru Mapel","pengawas_bidang_studi":null,"agama":"Hindu","kewarganegaraan":"ID","alamat_jalan":"RAMA GUNAWAN","rt":null,"rw":null,"nama_dusun":null,"desa_kelurahan":"RAMA GUNAWAN","kode_kecamatan":"120207  ","kecamatan":"Kec. Seputih Raman","kode_kabupaten":"120200  ","kabupaten":"Kab. Lampung Tengah","kode_provinsi":"120000  ","provinsi":"Prov. Lampung","kode_pos":null,"lintang":null,"bujur":null,"no_telepon_rumah":null,"no_hp":null,"email":"dwaraastarina02@yahoo.com","status_keaktifan":"Aktif","sk_cpns":null,"tgl_cpns":null,"sk_pengangkatan":"421.2/23/C.1/D.a.IV.01/2020","tmt_pengangkatan":"2020-07-16","lembaga_pengangkat":"Kepala Sekolah","pangkat_golongan":null,"keahlian_laboratorium":null,"sumber_gaji":"Sekolah","nama_ibu_kandung":"SUTARNI","status_perkawinan":"2","nama_suami_istri":null,"nip_suami_istri":null,"pekerjaan_suami_istri":99,"tmt_pns":null,"sudah_lisensi_kepala_sekolah":"0","jumlah_sekolah_binaan":null,"pernah_diklat_kepengawasan":"0","nm_wp":null,"status_data":null,"karpeg":null,"karpas":null,"mampu_handle_kk":"0","keahlian_braille":"0","keahlian_bhs_isyarat":"0","npwp":null,"bank":null,"rekening_bank":null,"rekening_atas_nama":null,"tahun_ajaran":"2022/2023","nomor_surat_tugas":"421.2/23/C.1/D.a.IV.01/2020","tanggal_surat_tugas":"2020-07-16","tmt_tugas":"2020-07-16","ptk_induk":"1","jenis_keluar":null,"tgl_ptk_keluar":null,"riwayat_kepangkatan_pangkat_golongan":null,"riwayat_kepangkatan_nomor_sk":null,"riwayat_kepangkatan_tanggal_sk":null,"riwayat_kepangkatan_tmt_pangkat":null,"riwayat_kepangkatan_masa_kerja_gol_tahun":null,"riwayat_kepangkatan_masa_kerja_gol_bulan":null,"riwayat_gaji_berkala_pangkat_golongan":null,"riwayat_gaji_berkala_nomor_sk":null,"riwayat_gaji_berkala_tanggal_sk":null,"riwayat_gaji_berkala_tmt_kgb":null,"riwayat_gaji_berkala_masa_kerja_tahun":null,"riwayat_gaji_berkala_masa_kerja_bulan":null,"riwayat_gaji_berkala_gaji_pokok":null,"inpassing_pangkat_golongan":null,"inpassing_no_sk_inpassing":null,"inpassing_tgl_sk_inpassing":null,"inpassing_tmt_inpassing":null,"inpassing_angka_kredit":null,"inpassing_masa_kerja_tahun":null,"inpassing_masa_kerja_bulan":null,"riwayat_sertifikasi_bidang_studi":null,"riwayat_sertifikasi_jenis_sertifikasi":null,"riwayat_sertifikasi_tahun_sertifikasi":null,"riwayat_sertifikasi_nomor_sertifikat":null,"riwayat_sertifikasi_nrg":null,"riwayat_sertifikasi_nomor_peserta":null,"riwayat_pendidikan_formal_bidang_studi":null,"riwayat_pendidikan_formal_jenjang_pendidikan":null,"riwayat_pendidikan_formal_gelar_akademik":null,"riwayat_pendidikan_formal_satuan_pendidikan_formal":null,"riwayat_pendidikan_formal_fakultas":null,"riwayat_pendidikan_formal_kependidikan":null,"riwayat_pendidikan_formal_tahun_masuk":null,"riwayat_pendidikan_formal_tahun_lulus":null,"riwayat_pendidikan_formal_nim":null,"riwayat_pendidikan_formal_status_kuliah":null,"riwayat_pendidikan_formal_semester":null,"riwayat_pendidikan_formal_ipk":null,"jumlah_anak":null,"tugas_tambahan_jabatan_ptk":null,"tugas_tambahan_sekolah":null,"tugas_tambahan_jumlah_jam":null,"tugas_tambahan_nomor_sk":null,"tugas_tambahan_tmt_tambahan":null,"tugas_tambahan_tst_tambahan":null,"riwayat_struktural_jabatan_ptk":null,"riwayat_struktural_sk_struktural":null,"riwayat_struktural_tmt_jabatan":null,"riwayat_fungsional_jabatan_fungsional":null,"riwayat_fungsional_sk_jabfung":null,"riwayat_fungsional_tmt_jabatan":null,"create_date":"2022-10-27T09:00:05.257000","last_update":"2022-10-27T09:30:07.973000","soft_delete_ptk_terdaftar":0,"soft_delete_rwy_kepangkatan":null,"soft_delete_riwayat_gaji_berkala":null,"soft_delete_inpassing":null,"soft_delete_rwy_sertifikasi":null,"soft_delete_rwy_pend_formal":null,"soft_delete_tugas_tambahan":null,"soft_delete_rwy_struktural":null,"soft_delete_rwy_fungsional":null},{"ptk_id":"f6e57801-e737-4d24-aff7-b471c918ee52","semester_id":"20222","sekolah_id":"c09cc86f-8b18-e111-b090-314ae660b182","ptk_terdaftar_id":"2cdf2164-26ea-434e-a91a-c0c8aea40f95","nama":"NI MADE LUSIANA","nip":"199402182022212009","jenis_kelamin":"P","tempat_lahir":"RAMA DEWA","tanggal_lahir":"1994-02-18","nik":"1802085802940001","no_kk":null,"niy_nigk":null,"nuptk":"8550772673130022","nuks":null,"status_kepegawaian":"PPPK","jenis_ptk_id":"4 ","jenis_ptk":"Guru Mapel","pengawas_bidang_studi":null,"agama":"Hindu","kewarganegaraan":"ID","alamat_jalan":"RAMA DEWA","rt":null,"rw":null,"nama_dusun":null,"desa_kelurahan":"RAMA DEWA","kode_kecamatan":"120207  ","kecamatan":"Kec. Seputih Raman","kode_kabupaten":"120200  ","kabupaten":"Kab. Lampung Tengah","kode_provinsi":"120000  ","provinsi":"Prov. Lampung","kode_pos":null,"lintang":null,"bujur":null,"no_telepon_rumah":null,"no_hp":null,"email":"madelusiana@gmail.com","status_keaktifan":"Aktif","sk_cpns":null,"tgl_cpns":null,"sk_pengangkatan":"810/431/B.a.VII.04/2022","tmt_pengangkatan":"2022-02-01","lembaga_pengangkat":"Pemerintah Kab/Kota","pangkat_golongan":null,"keahlian_laboratorium":"Lainnya","sumber_gaji":"APBD Kabupaten/Kota","nama_ibu_kandung":"NI KETUT NANTRI","status_perkawinan":"1","nama_suami_istri":null,"nip_suami_istri":null,"pekerjaan_suami_istri":90,"tmt_pns":"2022-02-01","sudah_lisensi_kepala_sekolah":"0","jumlah_sekolah_binaan":0,"pernah_diklat_kepengawasan":"0","nm_wp":null,"status_data":0,"karpeg":null,"karpas":null,"mampu_handle_kk":"0","keahlian_braille":"0","keahlian_bhs_isyarat":"0","npwp":null,"bank":null,"rekening_bank":null,"rekening_atas_nama":null,"tahun_ajaran":"2022/2023","nomor_surat_tugas":"421.2/66/C.10/D.1/2018","tanggal_surat_tugas":"2017-07-17","tmt_tugas":"2017-07-17","ptk_induk":"1","jenis_keluar":null,"tgl_ptk_keluar":null,"riwayat_kepangkatan_pangkat_golongan":null,"riwayat_kepangkatan_nomor_sk":null,"riwayat_kepangkatan_tanggal_sk":null,"riwayat_kepangkatan_tmt_pangkat":null,"riwayat_kepangkatan_masa_kerja_gol_tahun":null,"riwayat_kepangkatan_masa_kerja_gol_bulan":null,"riwayat_gaji_berkala_pangkat_golongan":null,"riwayat_gaji_berkala_nomor_sk":null,"riwayat_gaji_berkala_tanggal_sk":null,"riwayat_gaji_berkala_tmt_kgb":null,"riwayat_gaji_berkala_masa_kerja_tahun":null,"riwayat_gaji_berkala_masa_kerja_bulan":null,"riwayat_gaji_berkala_gaji_pokok":null,"inpassing_pangkat_golongan":null,"inpassing_no_sk_inpassing":null,"inpassing_tgl_sk_inpassing":null,"inpassing_tmt_inpassing":null,"inpassing_angka_kredit":null,"inpassing_masa_kerja_tahun":null,"inpassing_masa_kerja_bulan":null,"riwayat_sertifikasi_bidang_studi":null,"riwayat_sertifikasi_jenis_sertifikasi":null,"riwayat_sertifikasi_tahun_sertifikasi":null,"riwayat_sertifikasi_nomor_sertifikat":null,"riwayat_sertifikasi_nrg":null,"riwayat_sertifikasi_nomor_peserta":null,"riwayat_pendidikan_formal_bidang_studi":"Pendidikan Agama Hindu","riwayat_pendidikan_formal_jenjang_pendidikan":"S1","riwayat_pendidikan_formal_gelar_akademik":"Sarjana Pendidikan","riwayat_pendidikan_formal_satuan_pendidikan_formal":"","riwayat_pendidikan_formal_fakultas":"","riwayat_pendidikan_formal_kependidikan":"Ya","riwayat_pendidikan_formal_tahun_masuk":2013,"riwayat_pendidikan_formal_tahun_lulus":2018,"riwayat_pendidikan_formal_nim":"13101100283","riwayat_pendidikan_formal_status_kuliah":"Tidak","riwayat_pendidikan_formal_semester":0,"riwayat_pendidikan_formal_ipk":3.0,"jumlah_anak":null,"tugas_tambahan_jabatan_ptk":null,"tugas_tambahan_sekolah":null,"tugas_tambahan_jumlah_jam":null,"tugas_tambahan_nomor_sk":null,"tugas_tambahan_tmt_tambahan":null,"tugas_tambahan_tst_tambahan":null,"riwayat_struktural_jabatan_ptk":null,"riwayat_struktural_sk_struktural":null,"riwayat_struktural_tmt_jabatan":null,"riwayat_fungsional_jabatan_fungsional":null,"riwayat_fungsional_sk_jabfung":null,"riwayat_fungsional_tmt_jabatan":null,"create_date":"2019-08-30T12:21:22.297000","last_update":"2022-08-10T19:43:40.247000","soft_delete_ptk_terdaftar":0,"soft_delete_rwy_kepangkatan":null,"soft_delete_riwayat_gaji_berkala":null,"soft_delete_inpassing":null,"soft_delete_rwy_sertifikasi":null,"soft_delete_rwy_pend_formal":0,"soft_delete_tugas_tambahan":null,"soft_delete_rwy_struktural":null,"soft_delete_rwy_fungsional":null},{"ptk_id":"155cb616-ae07-e211-a8e5-df0543f6e3e9","semester_id":"20222","sekolah_id":"c09cc86f-8b18-e111-b090-314ae660b182","ptk_terdaftar_id":"233ebed4-8159-4b19-a693-56a27b0ea80f","nama":"Ni Wayan Sandri","nip":"196302111984032003","jenis_kelamin":"P","tempat_lahir":"RAMA DEWA","tanggal_lahir":"1963-02-11","nik":"1802085102630006","no_kk":null,"niy_nigk":null,"nuptk":"9543741642200012","nuks":null,"status_kepegawaian":"PNS","jenis_ptk_id":"4 ","jenis_ptk":"Guru Mapel","pengawas_bidang_studi":"lainnya","agama":"Hindu","kewarganegaraan":"ID","alamat_jalan":"RAMA DEWA","rt":4,"rw":2,"nama_dusun":"Dusun 4","desa_kelurahan":"RAMA DEWA","kode_kecamatan":"120207  ","kecamatan":"Kec. Seputih Raman","kode_kabupaten":"120200  ","kabupaten":"Kab. Lampung Tengah","kode_provinsi":"120000  ","provinsi":"Prov. Lampung","kode_pos":"34155","lintang":null,"bujur":null,"no_telepon_rumah":null,"no_hp":"082179197015","email":"niwayansandri@gmail.com","status_keaktifan":"Aktif","sk_cpns":"736/UP/1984","tgl_cpns":"1984-03-01","sk_pengangkatan":"736/UP/1984","tmt_pengangkatan":"1984-03-01","lembaga_pengangkat":"Pemerintah Pusat","pangkat_golongan":"IV/a","keahlian_laboratorium":"Lainnya","sumber_gaji":"APBD Kabupaten/Kota","nama_ibu_kandung":"NI KETUT RATI, Alm","status_perkawinan":"1","nama_suami_istri":"I WAYAN WIDIA","nip_suami_istri":"1952101019721010  ","pekerjaan_suami_istri":5,"tmt_pns":"1986-02-01","sudah_lisensi_kepala_sekolah":"1","jumlah_sekolah_binaan":0,"pernah_diklat_kepengawasan":"0","nm_wp":null,"status_data":0,"karpeg":null,"karpas":null,"mampu_handle_kk":"0","keahlian_braille":"0","keahlian_bhs_isyarat":"0","npwp":"675536304321000","bank":null,"rekening_bank":null,"rekening_atas_nama":null,"tahun_ajaran":"2022/2023","nomor_surat_tugas":"Kp140/105/VII/4/1984","tanggal_surat_tugas":"1984-09-28","tmt_tugas":"1984-10-01","ptk_induk":"1","jenis_keluar":null,"tgl_ptk_keluar":null,"riwayat_kepangkatan_pangkat_golongan":"IV/a","riwayat_kepangkatan_nomor_sk":"823.4/3056/II.12/2010","riwayat_kepangkatan_tanggal_sk":"2010-06-01","riwayat_kepangkatan_tmt_pangkat":"2010-04-01","riwayat_kepangkatan_masa_kerja_gol_tahun":21,"riwayat_kepangkatan_masa_kerja_gol_bulan":21,"riwayat_gaji_berkala_pangkat_golongan":"IV/a","riwayat_gaji_berkala_nomor_sk":"822.4/1676/B.a.VII.04/2017","riwayat_gaji_berkala_tanggal_sk":"2017-02-09","riwayat_gaji_berkala_tmt_kgb":"2017-03-01","riwayat_gaji_berkala_masa_kerja_tahun":28,"riwayat_gaji_berkala_masa_kerja_bulan":0,"riwayat_gaji_berkala_gaji_pokok":4475700,"inpassing_pangkat_golongan":"III/b","inpassing_no_sk_inpassing":"800/355/LTD.5/2003","inpassing_tgl_sk_inpassing":null,"inpassing_tmt_inpassing":"2003-01-01","inpassing_angka_kredit":0,"inpassing_masa_kerja_tahun":13,"inpassing_masa_kerja_bulan":10,"riwayat_sertifikasi_bidang_studi":"Pendidikan Agama Hindu","riwayat_sertifikasi_jenis_sertifikasi":"Sertifikasi Pendidik","riwayat_sertifikasi_tahun_sertifikasi":null,"riwayat_sertifikasi_nomor_sertifikat":"2191313700150","riwayat_sertifikasi_nrg":null,"riwayat_sertifikasi_nomor_peserta":"13120213720297","riwayat_pendidikan_formal_bidang_studi":null,"riwayat_pendidikan_formal_jenjang_pendidikan":null,"riwayat_pendidikan_formal_gelar_akademik":null,"riwayat_pendidikan_formal_satuan_pendidikan_formal":null,"riwayat_pendidikan_formal_fakultas":null,"riwayat_pendidikan_formal_kependidikan":null,"riwayat_pendidikan_formal_tahun_masuk":null,"riwayat_pendidikan_formal_tahun_lulus":null,"riwayat_pendidikan_formal_nim":null,"riwayat_pendidikan_formal_status_kuliah":null,"riwayat_pendidikan_formal_semester":null,"riwayat_pendidikan_formal_ipk":null,"jumlah_anak":3,"tugas_tambahan_jabatan_ptk":null,"tugas_tambahan_sekolah":null,"tugas_tambahan_jumlah_jam":null,"tugas_tambahan_nomor_sk":null,"tugas_tambahan_tmt_tambahan":null,"tugas_tambahan_tst_tambahan":null,"riwayat_struktural_jabatan_ptk":null,"riwayat_struktural_sk_struktural":null,"riwayat_struktural_tmt_jabatan":null,"riwayat_fungsional_jabatan_fungsional":null,"riwayat_fungsional_sk_jabfung":null,"riwayat_fungsional_tmt_jabatan":null,"create_date":"2018-01-24T11:23:02.553000","last_update":"2020-11-02T17:46:33.120000","soft_delete_ptk_terdaftar":0,"soft_delete_rwy_kepangkatan":0,"soft_delete_riwayat_gaji_berkala":0,"soft_delete_inpassing":0,"soft_delete_rwy_sertifikasi":0,"soft_delete_rwy_pend_formal":null,"soft_delete_tugas_tambahan":null,"soft_delete_rwy_struktural":null,"soft_delete_rwy_fungsional":null},{"ptk_id":"0d4c99f4-ad07-e211-a8e4-df0543f6e3e9","semester_id":"20222","sekolah_id":"c09cc86f-8b18-e111-b090-314ae660b182","ptk_terdaftar_id":"098d2a67-9d2c-4e17-832e-3e074a9ca83d","nama":"Ni Made Karti","nip":"196205021983032006","jenis_kelamin":"P","tempat_lahir":"RAMA DEWA","tanggal_lahir":"1962-05-02","nik":"1802084205620001","no_kk":null,"niy_nigk":null,"nuptk":"1834740642300042","nuks":null,"status_kepegawaian":"PNS","jenis_ptk_id":"3 ","jenis_ptk":"Guru Kelas","pengawas_bidang_studi":"lainnya","agama":"Hindu","kewarganegaraan":"ID","alamat_jalan":"RAMA DEWA","rt":3,"rw":2,"nama_dusun":"Dusun 3","desa_kelurahan":"RAMA DEWA","kode_kecamatan":"120207  ","kecamatan":"Kec. Seputih Raman","kode_kabupaten":"120200  ","kabupaten":"Kab. Lampung Tengah","kode_provinsi":"120000  ","provinsi":"Prov. Lampung","kode_pos":"34155","lintang":null,"bujur":null,"no_telepon_rumah":null,"no_hp":"081272257667","email":"nimade_karti62@yahoo.co.id","status_keaktifan":"Aktif","sk_cpns":"143/UP/1983","tgl_cpns":"1983-03-01","sk_pengangkatan":"143/UP/1983","tmt_pengangkatan":"1983-03-01","lembaga_pengangkat":"Pemerintah Pusat","pangkat_golongan":"IV/a","keahlian_laboratorium":"Lainnya","sumber_gaji":"APBD Kabupaten/Kota","nama_ibu_kandung":"MEN BERATA","status_perkawinan":"1","nama_suami_istri":"I NYOMAN WANISTARA","nip_suami_istri":null,"pekerjaan_suami_istri":3,"tmt_pns":"1985-01-01","sudah_lisensi_kepala_sekolah":"1","jumlah_sekolah_binaan":0,"pernah_diklat_kepengawasan":"0","nm_wp":null,"status_data":0,"karpeg":null,"karpas":null,"mampu_handle_kk":"0","keahlian_braille":"0","keahlian_bhs_isyarat":"0","npwp":"583909643321000","bank":null,"rekening_bank":null,"rekening_atas_nama":null,"tahun_ajaran":"2022/2023","nomor_surat_tugas":"821.29/937/01/2010","tanggal_surat_tugas":"2010-05-27","tmt_tugas":"2010-05-27","ptk_induk":"0","jenis_keluar":"Pensiun","tgl_ptk_keluar":"2022-05-02","riwayat_kepangkatan_pangkat_golongan":"IV/b","riwayat_kepangkatan_nomor_sk":"823.4/851/II.10/2016","riwayat_kepangkatan_tanggal_sk":"2016-08-15","riwayat_kepangkatan_tmt_pangkat":"2016-10-01","riwayat_kepangkatan_masa_kerja_gol_tahun":28,"riwayat_kepangkatan_masa_kerja_gol_bulan":7,"riwayat_gaji_berkala_pangkat_golongan":"IV/b","riwayat_gaji_berkala_nomor_sk":"823.4/0148/B.a.VII.04/2020","riwayat_gaji_berkala_tanggal_sk":"2020-01-06","riwayat_gaji_berkala_tmt_kgb":"2020-03-01","riwayat_gaji_berkala_masa_kerja_tahun":32,"riwayat_gaji_berkala_masa_kerja_bulan":0,"riwayat_gaji_berkala_gaji_pokok":5211500,"inpassing_pangkat_golongan":"III/c","inpassing_no_sk_inpassing":"800/355/LTD.5/2003","inpassing_tgl_sk_inpassing":null,"inpassing_tmt_inpassing":"2003-01-01","inpassing_angka_kredit":0,"inpassing_masa_kerja_tahun":14,"inpassing_masa_kerja_bulan":10,"riwayat_sertifikasi_bidang_studi":"Guru Kelas SD/MI","riwayat_sertifikasi_jenis_sertifikasi":"Sertifikasi Pendidik","riwayat_sertifikasi_tahun_sertifikasi":null,"riwayat_sertifikasi_nomor_sertifikat":"1071202704763","riwayat_sertifikasi_nrg":null,"riwayat_sertifikasi_nomor_peserta":"12120202710840","riwayat_pendidikan_formal_bidang_studi":null,"riwayat_pendidikan_formal_jenjang_pendidikan":null,"riwayat_pendidikan_formal_gelar_akademik":null,"riwayat_pendidikan_formal_satuan_pendidikan_formal":null,"riwayat_pendidikan_formal_fakultas":null,"riwayat_pendidikan_formal_kependidikan":null,"riwayat_pendidikan_formal_tahun_masuk":null,"riwayat_pendidikan_formal_tahun_lulus":null,"riwayat_pendidikan_formal_nim":null,"riwayat_pendidikan_formal_status_kuliah":null,"riwayat_pendidikan_formal_semester":null,"riwayat_pendidikan_formal_ipk":null,"jumlah_anak":3,"tugas_tambahan_jabatan_ptk":null,"tugas_tambahan_sekolah":null,"tugas_tambahan_jumlah_jam":null,"tugas_tambahan_nomor_sk":null,"tugas_tambahan_tmt_tambahan":null,"tugas_tambahan_tst_tambahan":null,"riwayat_struktural_jabatan_ptk":"Guru","riwayat_struktural_sk_struktural":"****","riwayat_struktural_tmt_jabatan":"2008-04-01","riwayat_fungsional_jabatan_fungsional":null,"riwayat_fungsional_sk_jabfung":null,"riwayat_fungsional_tmt_jabatan":null,"create_date":"2018-01-24T11:23:02.553000","last_update":"2020-11-02T17:46:33.120000","soft_delete_ptk_terdaftar":0,"soft_delete_rwy_kepangkatan":0,"soft_delete_riwayat_gaji_berkala":0,"soft_delete_inpassing":0,"soft_delete_rwy_sertifikasi":0,"soft_delete_rwy_pend_formal":null,"soft_delete_tugas_tambahan":null,"soft_delete_rwy_struktural":0,"soft_delete_rwy_fungsional":null},{"ptk_id":"a84f170a-ae07-e211-a8e5-df0543f6e3e9","semester_id":"20222","sekolah_id":"c09cc86f-8b18-e111-b090-314ae660b182","ptk_terdaftar_id":"d13578fc-84f5-4e32-aadc-e80bab201d2a","nama":"Ni Nengah Sunarti","nip":"196203051983032008","jenis_kelamin":"P","tempat_lahir":"RAMA DEWA","tanggal_lahir":"1962-03-05","nik":"1802084503620004","no_kk":null,"niy_nigk":null,"nuptk":"6637740642300032","nuks":null,"status_kepegawaian":"PNS","jenis_ptk_id":"3 ","jenis_ptk":"Guru Kelas","pengawas_bidang_studi":"lainnya","agama":"Hindu","kewarganegaraan":"ID","alamat_jalan":"RAMA DEWA","rt":1,"rw":4,"nama_dusun":"Dusun IV","desa_kelurahan":"RAMA DEWA","kode_kecamatan":"120207  ","kecamatan":"Kec. Seputih Raman","kode_kabupaten":"120200  ","kabupaten":"Kab. Lampung Tengah","kode_provinsi":"120000  ","provinsi":"Prov. Lampung","kode_pos":"34155","lintang":null,"bujur":null,"no_telepon_rumah":null,"no_hp":"081379280377","email":"ninengah_sunarti@yahoo.co.id","status_keaktifan":"Aktif","sk_cpns":"143/UP/1983","tgl_cpns":"1983-03-01","sk_pengangkatan":"143/UP/1983","tmt_pengangkatan":"1983-03-01","lembaga_pengangkat":"Pemerintah Pusat","pangkat_golongan":"IV/a","keahlian_laboratorium":"Lainnya","sumber_gaji":"APBD Kabupaten/Kota","nama_ibu_kandung":"NI KETUT RAYUG","status_perkawinan":"3","nama_suami_istri":null,"nip_suami_istri":null,"pekerjaan_suami_istri":99,"tmt_pns":"1985-01-01","sudah_lisensi_kepala_sekolah":"1","jumlah_sekolah_binaan":0,"pernah_diklat_kepengawasan":"0","nm_wp":null,"status_data":0,"karpeg":null,"karpas":null,"mampu_handle_kk":"0","keahlian_braille":"0","keahlian_bhs_isyarat":"0","npwp":null,"bank":null,"rekening_bank":null,"rekening_atas_nama":null,"tahun_ajaran":"2022/2023","nomor_surat_tugas":"Kp140/1553/1V/3/1983","tanggal_surat_tugas":"1983-08-31","tmt_tugas":"1983-09-01","ptk_induk":"0","jenis_keluar":"Pensiun","tgl_ptk_keluar":"2022-03-05","riwayat_kepangkatan_pangkat_golongan":"IV/a","riwayat_kepangkatan_nomor_sk":"823.4/3456/11.12/2010","riwayat_kepangkatan_tanggal_sk":"2010-06-01","riwayat_kepangkatan_tmt_pangkat":"2010-04-01","riwayat_kepangkatan_masa_kerja_gol_tahun":2,"riwayat_kepangkatan_masa_kerja_gol_bulan":2,"riwayat_gaji_berkala_pangkat_golongan":"IV/a","riwayat_gaji_berkala_nomor_sk":"823.4/0607/B.a.VII.04/2020","riwayat_gaji_berkala_tanggal_sk":"2020-01-06","riwayat_gaji_berkala_tmt_kgb":"2020-03-01","riwayat_gaji_berkala_masa_kerja_tahun":32,"riwayat_gaji_berkala_masa_kerja_bulan":0,"riwayat_gaji_berkala_gaji_pokok":5000000,"inpassing_pangkat_golongan":"III/b","inpassing_no_sk_inpassing":"800/355/LTD.5/2003","inpassing_tgl_sk_inpassing":null,"inpassing_tmt_inpassing":"2003-01-01","inpassing_angka_kredit":0,"inpassing_masa_kerja_tahun":14,"inpassing_masa_kerja_bulan":10,"riwayat_sertifikasi_bidang_studi":"Guru Kelas SD/MI","riwayat_sertifikasi_jenis_sertifikasi":"Sertifikasi Pendidik","riwayat_sertifikasi_tahun_sertifikasi":null,"riwayat_sertifikasi_nomor_sertifikat":"1071302702918","riwayat_sertifikasi_nrg":null,"riwayat_sertifikasi_nomor_peserta":"13120202711103","riwayat_pendidikan_formal_bidang_studi":null,"riwayat_pendidikan_formal_jenjang_pendidikan":null,"riwayat_pendidikan_formal_gelar_akademik":null,"riwayat_pendidikan_formal_satuan_pendidikan_formal":null,"riwayat_pendidikan_formal_fakultas":null,"riwayat_pendidikan_formal_kependidikan":null,"riwayat_pendidikan_formal_tahun_masuk":null,"riwayat_pendidikan_formal_tahun_lulus":null,"riwayat_pendidikan_formal_nim":null,"riwayat_pendidikan_formal_status_kuliah":null,"riwayat_pendidikan_formal_semester":null,"riwayat_pendidikan_formal_ipk":null,"jumlah_anak":2,"tugas_tambahan_jabatan_ptk":null,"tugas_tambahan_sekolah":null,"tugas_tambahan_jumlah_jam":null,"tugas_tambahan_nomor_sk":null,"tugas_tambahan_tmt_tambahan":null,"tugas_tambahan_tst_tambahan":null,"riwayat_struktural_jabatan_ptk":"Guru","riwayat_struktural_sk_struktural":"****","riwayat_struktural_tmt_jabatan":"1983-03-01","riwayat_fungsional_jabatan_fungsional":null,"riwayat_fungsional_sk_jabfung":null,"riwayat_fungsional_tmt_jabatan":null,"create_date":"2018-01-24T11:23:02.553000","last_update":"2020-11-02T17:46:33.120000","soft_delete_ptk_terdaftar":0,"soft_delete_rwy_kepangkatan":0,"soft_delete_riwayat_gaji_berkala":0,"soft_delete_inpassing":0,"soft_delete_rwy_sertifikasi":0,"soft_delete_rwy_pend_formal":null,"soft_delete_tugas_tambahan":null,"soft_delete_rwy_struktural":0,"soft_delete_rwy_fungsional":null}]