[{"ptk_id":"efb8c8c9-23b5-47c9-8030-438e3ca1a008","semester_id":"20222","sekolah_id":"3f2c2cd4-7863-4201-92e9-a6b1af448ebd","ptk_terdaftar_id":"bb90681b-ef04-4ff3-8cbb-4777ba31df5d","nama":"SAMSIYAH","nip":null,"jenis_kelamin":"P","tempat_lahir":"Dono Arum","tanggal_lahir":"1969-04-10","nik":"1802215004690002","no_kk":null,"niy_nigk":null,"nuptk":null,"nuks":null,"status_kepegawaian":"Guru Honor Sekolah","jenis_ptk_id":"20","jenis_ptk":"Kepala Sekolah","pengawas_bidang_studi":"Guru Kelas PAUD","agama":"Islam","kewarganegaraan":"ID","alamat_jalan":"Jl. Sri Marga Rahayu","rt":6,"rw":4,"nama_dusun":"Sri Marga Rahayu","desa_kelurahan":"Negara Bumi Udik","kode_kecamatan":"120219  ","kecamatan":"Kec. Anak Tuha","kode_kabupaten":"120200  ","kabupaten":"Kab. Lampung Tengah","kode_provinsi":"120000  ","provinsi":"Prov. Lampung","kode_pos":"34176","lintang":null,"bujur":null,"no_telepon_rumah":null,"no_hp":null,"email":"siyahsam400@gmail.com","status_keaktifan":"Aktif","sk_cpns":null,"tgl_cpns":null,"sk_pengangkatan":"420/002/PKBM/KH/NBU/2009","tmt_pengangkatan":"2009-07-17","lembaga_pengangkat":"Kepala Sekolah","pangkat_golongan":null,"keahlian_laboratorium":"Lainnya","sumber_gaji":"Sekolah","nama_ibu_kandung":"Kasmi","status_perkawinan":"1","nama_suami_istri":"Mat Ridwan","nip_suami_istri":null,"pekerjaan_suami_istri":9,"tmt_pns":null,"sudah_lisensi_kepala_sekolah":"0","jumlah_sekolah_binaan":0,"pernah_diklat_kepengawasan":"0","nm_wp":null,"status_data":0,"karpeg":null,"karpas":null,"mampu_handle_kk":"0","keahlian_braille":"0","keahlian_bhs_isyarat":"0","npwp":null,"bank":null,"rekening_bank":null,"rekening_atas_nama":null,"tahun_ajaran":"2022/2023","nomor_surat_tugas":"420/23/PKBM/KH/NBU/2017","tanggal_surat_tugas":"2022-07-12","tmt_tugas":"2009-07-17","ptk_induk":"1","jenis_keluar":null,"tgl_ptk_keluar":null,"riwayat_kepangkatan_pangkat_golongan":null,"riwayat_kepangkatan_nomor_sk":null,"riwayat_kepangkatan_tanggal_sk":null,"riwayat_kepangkatan_tmt_pangkat":null,"riwayat_kepangkatan_masa_kerja_gol_tahun":null,"riwayat_kepangkatan_masa_kerja_gol_bulan":null,"riwayat_gaji_berkala_pangkat_golongan":null,"riwayat_gaji_berkala_nomor_sk":null,"riwayat_gaji_berkala_tanggal_sk":null,"riwayat_gaji_berkala_tmt_kgb":null,"riwayat_gaji_berkala_masa_kerja_tahun":null,"riwayat_gaji_berkala_masa_kerja_bulan":null,"riwayat_gaji_berkala_gaji_pokok":null,"inpassing_pangkat_golongan":null,"inpassing_no_sk_inpassing":null,"inpassing_tgl_sk_inpassing":null,"inpassing_tmt_inpassing":null,"inpassing_angka_kredit":null,"inpassing_masa_kerja_tahun":null,"inpassing_masa_kerja_bulan":null,"riwayat_sertifikasi_bidang_studi":null,"riwayat_sertifikasi_jenis_sertifikasi":null,"riwayat_sertifikasi_tahun_sertifikasi":null,"riwayat_sertifikasi_nomor_sertifikat":null,"riwayat_sertifikasi_nrg":null,"riwayat_sertifikasi_nomor_peserta":null,"riwayat_pendidikan_formal_bidang_studi":"Guru Kelas PAUD","riwayat_pendidikan_formal_jenjang_pendidikan":"SMA / sederajat","riwayat_pendidikan_formal_gelar_akademik":"Sarjana Manajemen","riwayat_pendidikan_formal_satuan_pendidikan_formal":"-","riwayat_pendidikan_formal_fakultas":"","riwayat_pendidikan_formal_kependidikan":"Tidak","riwayat_pendidikan_formal_tahun_masuk":1990,"riwayat_pendidikan_formal_tahun_lulus":1993,"riwayat_pendidikan_formal_nim":"-","riwayat_pendidikan_formal_status_kuliah":"Tidak","riwayat_pendidikan_formal_semester":0,"riwayat_pendidikan_formal_ipk":0.0,"jumlah_anak":null,"tugas_tambahan_jabatan_ptk":"Kepala Sekolah","tugas_tambahan_sekolah":"(69919328) KB BUNDA","tugas_tambahan_jumlah_jam":18,"tugas_tambahan_nomor_sk":"-","tugas_tambahan_tmt_tambahan":"2009-07-17","tugas_tambahan_tst_tambahan":null,"riwayat_struktural_jabatan_ptk":null,"riwayat_struktural_sk_struktural":null,"riwayat_struktural_tmt_jabatan":null,"riwayat_fungsional_jabatan_fungsional":null,"riwayat_fungsional_sk_jabfung":null,"riwayat_fungsional_tmt_jabatan":null,"create_date":"2018-02-06T22:30:48.240000","last_update":"2022-02-03T17:29:42.060000","soft_delete_ptk_terdaftar":0,"soft_delete_rwy_kepangkatan":null,"soft_delete_riwayat_gaji_berkala":null,"soft_delete_inpassing":null,"soft_delete_rwy_sertifikasi":null,"soft_delete_rwy_pend_formal":0,"soft_delete_tugas_tambahan":0,"soft_delete_rwy_struktural":null,"soft_delete_rwy_fungsional":null},{"ptk_id":"6ed682e6-ddb0-4682-a5b4-dab3ea9e36ae","semester_id":"20222","sekolah_id":"3f2c2cd4-7863-4201-92e9-a6b1af448ebd","ptk_terdaftar_id":"e43db4bf-ae53-41ea-8f95-fd571c2a8a48","nama":"TRI MULYANI","nip":null,"jenis_kelamin":"P","tempat_lahir":"Dono Arum","tanggal_lahir":"1978-04-13","nik":"1802215304780005","no_kk":null,"niy_nigk":null,"nuptk":null,"nuks":null,"status_kepegawaian":"Guru Honor Sekolah","jenis_ptk_id":"3 ","jenis_ptk":"Guru Kelas","pengawas_bidang_studi":"Guru Kelas PAUD","agama":"Islam","kewarganegaraan":"ID","alamat_jalan":"Jl. Sri Marga Rahayu","rt":8,"rw":3,"nama_dusun":"Negara Bumi Udik","desa_kelurahan":"Negara Bumi Udik","kode_kecamatan":"120219  ","kecamatan":"Kec. Anak Tuha","kode_kabupaten":"120200  ","kabupaten":"Kab. Lampung Tengah","kode_provinsi":"120000  ","provinsi":"Prov. Lampung","kode_pos":"34176","lintang":null,"bujur":null,"no_telepon_rumah":null,"no_hp":null,"email":"trimulyani0413@gmail.com","status_keaktifan":"Aktif","sk_cpns":null,"tgl_cpns":null,"sk_pengangkatan":"420/015/PKBM/KH/NBU/2016","tmt_pengangkatan":"2016-07-13","lembaga_pengangkat":"Ketua Yayasan","pangkat_golongan":null,"keahlian_laboratorium":"Lainnya","sumber_gaji":"Sekolah","nama_ibu_kandung":"Warisem","status_perkawinan":"1","nama_suami_istri":"Mashuri","nip_suami_istri":null,"pekerjaan_suami_istri":9,"tmt_pns":null,"sudah_lisensi_kepala_sekolah":"0","jumlah_sekolah_binaan":0,"pernah_diklat_kepengawasan":"0","nm_wp":null,"status_data":0,"karpeg":null,"karpas":null,"mampu_handle_kk":"0","keahlian_braille":"0","keahlian_bhs_isyarat":"0","npwp":null,"bank":null,"rekening_bank":null,"rekening_atas_nama":null,"tahun_ajaran":"2022/2023","nomor_surat_tugas":"420/001/01/C.21/2015","tanggal_surat_tugas":"2022-07-12","tmt_tugas":"2009-07-17","ptk_induk":"1","jenis_keluar":null,"tgl_ptk_keluar":null,"riwayat_kepangkatan_pangkat_golongan":null,"riwayat_kepangkatan_nomor_sk":null,"riwayat_kepangkatan_tanggal_sk":null,"riwayat_kepangkatan_tmt_pangkat":null,"riwayat_kepangkatan_masa_kerja_gol_tahun":null,"riwayat_kepangkatan_masa_kerja_gol_bulan":null,"riwayat_gaji_berkala_pangkat_golongan":null,"riwayat_gaji_berkala_nomor_sk":null,"riwayat_gaji_berkala_tanggal_sk":null,"riwayat_gaji_berkala_tmt_kgb":null,"riwayat_gaji_berkala_masa_kerja_tahun":null,"riwayat_gaji_berkala_masa_kerja_bulan":null,"riwayat_gaji_berkala_gaji_pokok":null,"inpassing_pangkat_golongan":null,"inpassing_no_sk_inpassing":null,"inpassing_tgl_sk_inpassing":null,"inpassing_tmt_inpassing":null,"inpassing_angka_kredit":null,"inpassing_masa_kerja_tahun":null,"inpassing_masa_kerja_bulan":null,"riwayat_sertifikasi_bidang_studi":null,"riwayat_sertifikasi_jenis_sertifikasi":null,"riwayat_sertifikasi_tahun_sertifikasi":null,"riwayat_sertifikasi_nomor_sertifikat":null,"riwayat_sertifikasi_nrg":null,"riwayat_sertifikasi_nomor_peserta":null,"riwayat_pendidikan_formal_bidang_studi":"Guru Kelas PAUD","riwayat_pendidikan_formal_jenjang_pendidikan":"SMA / sederajat","riwayat_pendidikan_formal_gelar_akademik":"Sarjana Manajemen","riwayat_pendidikan_formal_satuan_pendidikan_formal":"-","riwayat_pendidikan_formal_fakultas":"","riwayat_pendidikan_formal_kependidikan":"Tidak","riwayat_pendidikan_formal_tahun_masuk":1993,"riwayat_pendidikan_formal_tahun_lulus":1996,"riwayat_pendidikan_formal_nim":"-","riwayat_pendidikan_formal_status_kuliah":"Tidak","riwayat_pendidikan_formal_semester":0,"riwayat_pendidikan_formal_ipk":0.0,"jumlah_anak":null,"tugas_tambahan_jabatan_ptk":"Bendahara BOS","tugas_tambahan_sekolah":"(69919328) KB BUNDA","tugas_tambahan_jumlah_jam":0,"tugas_tambahan_nomor_sk":"34/2021","tugas_tambahan_tmt_tambahan":"2021-01-04","tugas_tambahan_tst_tambahan":null,"riwayat_struktural_jabatan_ptk":null,"riwayat_struktural_sk_struktural":null,"riwayat_struktural_tmt_jabatan":null,"riwayat_fungsional_jabatan_fungsional":null,"riwayat_fungsional_sk_jabfung":null,"riwayat_fungsional_tmt_jabatan":null,"create_date":"2018-02-06T22:30:48.240000","last_update":"2022-02-03T17:29:42.060000","soft_delete_ptk_terdaftar":0,"soft_delete_rwy_kepangkatan":null,"soft_delete_riwayat_gaji_berkala":null,"soft_delete_inpassing":null,"soft_delete_rwy_sertifikasi":null,"soft_delete_rwy_pend_formal":0,"soft_delete_tugas_tambahan":0,"soft_delete_rwy_struktural":null,"soft_delete_rwy_fungsional":null}]